{"Transitorio": {"transitorios_art\u00e3": 1, "\u00ad": 90, "culo": 56, "primero": 2, "": 343, "el": 252, "presente": 22, "decreto": 29, "entrar\u00e3": 10, "\u00a1": 23, "en": 64, "vigor": 11, "a": 78, "siguiente": 11, "d\u00e3": 13, "de": 89, "su": 22, "publicaci\u00e3": 20, "\u00b3": 106, "n": 109, "diario_oficial_de_la_federaci\u00e3": 19, "art\u00e3": 46, "segundo": 4, "comisi\u00e3": 1, "nacional_de_los_derechos_humanos": 1, "operar\u00e3": 1, "\u00e3": 7, "reo": 1, "correspondiente": 1, "observancia": 11, "dar": 2, "seguimiento": 1, "evaluaci\u00e3": 1, "y": 74, "monitoreo": 1, "materia": 1, "que": 12, "expresamente": 1, "le": 2, "conferir": 1, "este": 1, "ley": 1, "ser": 2, "requerir": 1, "opini\u00e3": 1, "entrada": 1, "m\u00e3": 8, "\u00a9": 31, "xico": 20, "df": 7, "[??:27/4/2006:????:??]": 1, "-": 103, "dip": 20, "marcela_gonz\u00e3": 1, "lez": 3, "salas_p": 1, "presidenta": 1, "sen": 20, "enrique_jackson_ram\u00e3": 1, "rez": 3, "presidente": 19, "marcos_morales_torres": 1, "secretario": 8, "sa\u00e3\u00bal_l\u00e3": 1, "pez": 1, "sollano": 1, "r\u00e3\u00babricas": 10, "\"": 10, "cumplimiento": 11, "disponer": 10, "por": 20, "fracci\u00e3": 34, "i_de_el_art\u00e3": 10, "89": 10, "constituci\u00e3": 10, "pol\u00e3": 10, "tic_a": 10, "estados_unidos_mexicanos": 10, "para": 21, "deber": 10, "expedir": 10, "residencia_de_el_poder_ejecutivo_federal": 10, "ciudad_de_m\u00e3": 13, "distrito_federal": 7, "27": 1, "as": 2, "[??:??/7/2006:????:??]": 1, "vicente_fox_quesada": 1, "r\u00e3\u00babrica": 19, "secretario_de_gobernaci\u00e3": 10, "carlos_mar\u00e3": 1, "abascal_carranza": 1, "\u008d": 2, "culos_transitorios_de_decretos_de_reforma_decreto": 1, "se": 25, "reformar": 8, "diverso": 3, "disposici\u00f3n": 4, "ley_general_para_la_igualdad": 18, "entre": 18, "mujeres": 18, "hombres": 18, "ley_de_vivienda": 1, "ley_federal_de_fomento": 1, "actividades": 1, "realizar": 1, "organizaciones_de_la_sociedad_civil": 1, "publicar": 9, "[??:16/6/2011:????:??]": 1, "reforma": 6, "p\u00e3": 3, "rrafo": 2, "1": 4, "3": 1, "quedar": 9, "como": 9, "seguir": 9, ":": 9, "\u00e2": 27, "\u0080": 27, "\u00a6": 27, "transitorio_\u00e3": 8, "\u009a": 15, "no": 12, "[??:22/3/2011:????:??]": 1, "jorge_carlos_ramirez_marin": 1, "manlio_fabio_beltrones_rivera": 1, "maria_dolores_de_el_rio_sanchez": 1, "secretaria": 12, "martha_leticia_sosa_govea": 1, "[??:15/6/2011:????:??]": 1, "felipe_de_jes\u00e3\u00bas_calder\u00e3": 2, "hinojosa": 2, "jos\u00e3": 3, "francisco_blake_mora": 1, "adicionar": 11, "i_bis": 2, "15": 2, "[??:6/3/2012:????:??]": 1, "nico": 3, "[??:1/2/2012:????:??]": 1, "guadalupe_acosta_naranjo": 1, "gonz\u00e3": 1, "morf\u00e3": 1, "gloria_romero_le\u00e3": 1, "ren\u00e3": 1, "cleominio_zoreda_novelo": 1, "[??:2/3/2012:????:??]": 1, "alejandro_alfonso_poir\u00e3": 1, "romero": 1, "r\u00e3\u00babrica_decreto": 1, "[??:14/11/2013:????:??]": 1, ";": 13, "i": 2, "actual": 1, "fracci\u00f3n": 12, "ii": 5, "iii": 5, "pasar": 1, "vii": 4, "viii": 2, "5": 2, "v": 6, "vi": 4, "17": 6, "33": 3, "x": 5, "xi": 7, "34": 5, "37": 2, "ix": 2, "40": 4, "42": 4, "iv": 6, "recorri\u00e3": 1, "ndose": 1, "subsecuente": 1, "uno": 10, "xii": 3, "[??:8/10/2013:????:??]": 1, "ra\u00e3\u00bal_cervantes_andrade": 1, "ricardo_anaya_cort\u00e3": 1, "lilia_guadalupe_merodio_reza": 2, "angelina_carre\u00e3": 1, "\u00b1": 10, "o": 1, "mijares": 1, "[??:12/11/2013:????:??]": 1, "enrique_pe\u00e3": 7, "nieto": 7, "miguel_\u00e3": 5, "\u0081": 5, "n_gel": 5, "osorio_chong": 5, "14": 1, "ley_de_adquisiciones": 1, "arrendamientos": 1, "servicios_de_el_sector_p\u00e3\u00bablico": 1, "[??:10/11/2014:????:??]": 1, "xi_de_el_art\u00e3": 1, "transitorios_primero": 1, "2": 1, "dependencia": 1, "administraci\u00e3": 1, "p\u00e3\u00bablica_federal": 1, "estatal": 1, "coordinaci\u00e3": 1, "con": 1, "secretar\u00e3": 2, "trabajo": 1, "previsi\u00e3": 1, "social": 1, "econom\u00e3": 1, "instituto_nacional_de_las_mujeres": 1, "deber\u00e3": 1, "adecuar": 1, "norma": 1, "oficial": 1, "mexicano": 1, "modelo": 1, "proceso": 1, "manual": 1, "certificaci\u00e3": 1, "existente": 1, "a_fin_de": 1, "establecer": 1, "plazo": 1, "ximo": 1, "90": 1, "contar": 1, "a_partir_de": 1, "inicio": 1, "vigencia": 1, "atender": 1, "aplicabilidad": 1, "principio": 1, "progresividad": 1, "[??:9/10/2014:????:??]": 1, "miguel_barbosa_huerta": 3, "silvano_aureoles_conejo": 2, "laura_barrera_fortoul": 1, "[??:5/11/2014:????:??]": 1, "[??:5/12/2014:????:??]": 1, "culo_\u00e3": 1, "[??:16/10/2014:????:??]": 1, "fernando_bribiesca_sahag\u00e3\u00ban": 1, "mar\u00e3": 1, "elena_barrera_tapia": 1, "[??:4/12/2014:????:??]": 1, "16": 2, "38": 2, "[??:4/6/2015:????:??]": 1, "[??:23/4/2015:????:??]": 1, "[??:??/7/??:????:??]": 1, "c\u00e3": 2, "sar": 2, "moreno_rivera": 1, "luis_antonio_gonz\u00e3": 1, "rold\u00e3": 1, "lucero_salda\u00e3": 1, "[??:??/6/2015:????:??]": 1, "[??:24/3/2016:????:??]": 1, "[??:17/2/2016:????:??]": 1, "jes\u00e3\u00bas_zambrano_grijalva": 1, "roberto_gil_zuarth": 1, "ram\u00e3": 1, "ba\u00e3": 1, "ale": 1, "arambula": 1, "octavio_pedroza_gait\u00e3": 1, "veintid\u00e3": 1, "[??:??/3/2000:????:??]": 1, "diecis\u00e3": 1, "9": 2, "xiii": 3, "[??:23/4/2018:????:??]": 1, "[??:8/3/2018:????:??]": 1, "ernesto_cordero_arroyo": 2, "edgar_romo_garc\u00e3": 2, "lorena_cu\u00e3": 1, "llar": 1, "cisneros": 1, "alejandra_noem\u00e3": 1, "reynoso_s\u00e3": 1, "nchez": 1, "[??:17/4/2018:????:??]": 1, "dr_jes\u00e3\u00bas_alfonso_navarrete_prida": 2, "[??:14/6/2018:????:??]": 1, "[??:26/4/2018:????:??]": 1, "juan_gerardo_flores_ram\u00e3": 1, "ana_guadalupe_perea_santos": 1, "[??:13/6/2018:????:??]": 1}}