{"Transitorio": {"decreto": 588, "por": 473, "el": 2036, "que": 956, "se": 784, "reforman": 59, "los": 1340, "art\u00e3\u00adculos": 60, "41": 14, "54": 3, "56": 3, "60": 5, "63": 2, "74": 15, "y": 1475, "100": 4, "de": 4953, "la": 2705, "constituci\u00e3\u00b3n": 390, "pol\u00e3\u00adtica": 326, "estados": 322, "unidos": 291, "mexicanos": 306, "publicado": 109, "en": 1874, "diario": 218, "oficial": 214, "federaci\u00e3\u00b3n": 257, "3": 13, "septiembre": 28, "1993": 3, "transitorios": 69, "art\u00e3\u00adculo": 710, "primero-": 37, "presente": 410, "entrar\u00e3\u00a1": 105, "vigor": 295, "d\u00e3\u00ada": 122, "su": 463, "publicaci\u00e3\u00b3n": 217, "segundo-": 34, "permanecer\u00e3\u00a1n": 3, "sus": 164, "cargos": 13, "actuales": 22, "magistrados": 16, "del": 1294, "tribunal": 21, "federal": 431, "electoral": 81, "electos": 8, "c\u00e3\u00a1mara": 41, "diputados": 36, "congreso": 115, "uni\u00e3\u00b3n": 93, "seg\u00e3\u00ban": 8, "octubre": 22, "1990": 2, "tercero-": 26, "elecci\u00e3\u00b3n": 24, "1994": 6, "elegir\u00e3\u00a1n": 5, "para": 595, "cada": 37, "estado": 43, "distrito": 169, "dos": 132, "senadores": 19, "mayor\u00e3\u00ada": 7, "relativa": 4, "uno": 13, "primera": 18, "minor\u00e3\u00ada": 1, "a": 1168, "las": 717, "legislaturas": 27, "lvi": 3, "lvii": 2, "quienes": 7, "durar\u00e3\u00a1n": 7, "funciones": 50, "1o": 19, "noviembre": 33, "fecha": 40, "t\u00e3\u00a9rmino": 2, "ejercicio": 38, "\u00e3\u00baltima": 4, "legislatura": 14, "citada": 3, "esta": 88, "partidos": 18, "pol\u00e3\u00adticos": 18, "deber\u00e3\u00a1n": 79, "registrar": 1, "una": 106, "lista": 6, "con": 252, "f\u00e3\u00b3rmulas": 6, "candidatos": 21, "entidad": 13, "federativa": 3, "cuarto-": 19, "federales": 25, "encargo": 28, "concluya": 4, "quinto-": 15, "integrar": 5, "h": 3, "realizar\u00e3\u00a1": 22, "base": 64, "distribuci\u00e3\u00b3n": 11, "distritos": 3, "uninominales": 3, "cinco": 14, "circunscripciones": 1, "plurinominales": 1, "dividi\u00e3\u00b3": 1, "pa\u00e3\u00ads": 12, "proceso": 30, "1991": 2, "1997": 17, "integrar\u00e3\u00a1": 3, "har\u00e3\u00a1": 10, "nueva": 3, "resultados": 5, "definitivos": 1, "censo": 2, "general": 62, "poblaci\u00e3\u00b3n": 8, "sexto-": 13, "derogan": 18, "todas": 19, "disposiciones": 97, "opongan": 9, "reformas": 35, "establecidas": 6, "salon": 13, "sesiones": 25, "comision": 13, "permanente": 25, "union-": 13, "m\u00e3\u00a9xico": 241, "df": 86, "2": 19, "1993-": 1, "sen": 135, "emilio": 3, "m": 1, "gonz\u00e3\u00a1lez": 14, "presidente-": 112, "antonio": 2, "melgar": 1, "aranda": 1, "secretario-": 72, "dip": 126, "juan": 11, "campos": 6, "vega": 3, "r\u00e3\u00babricas\"": 90, "cumplimiento": 129, "lo": 290, "dispuesto": 144, "fracci\u00e3\u00b3n": 381, "i": 142, "89": 106, "debida": 97, "observancia": 98, "expido": 96, "residencia": 96, "poder": 111, "ejecutivo": 138, "ciudad": 148, "d\u00e3\u00adas": 122, "mes": 43, "mil": 93, "novecientos": 10, "noventa": 12, "tres-": 1, "secretario": 101, "gobernaci\u00e3\u00b3n": 97, "jos\u00e3\u00a9": 20, "patrocinio": 1, "blanco": 2, "garrido-": 1, "r\u00e3\u00babrica": 95, "31": 21, "44": 1, "73": 84, "79": 12, "104": 7, "105": 18, "107": 7, "122": 24, "as\u00e3\u00ad": 87, "como": 220, "denominaci\u00e3\u00b3n": 9, "t\u00e3\u00adtulo": 7, "quinto": 52, "adici\u00e3\u00b3n": 6, "ix": 12, "al": 443, "76": 16, "un": 229, "primer": 51, "p\u00e3\u00a1rrafo": 292, "119": 3, "deroga": 14, "xvii": 5, "25": 11, "treinta": 15, "despu\u00e3\u00a9s": 10, "salvo": 19, "siguientes": 65, "asamblea": 46, "representantes": 9, "electa": 1, "per\u00e3\u00adodo": 13, "continuar\u00e3\u00a1": 14, "teniendo": 2, "facultades": 23, "vi": 28, "vigentes": 35, "momento": 25, "entrar": 9, "iii": 47, "tendr\u00e3\u00a1": 9, "le": 10, "otorga": 5, "ser\u00e3\u00a1": 43, "integre": 2, "comenzar\u00e3\u00a1": 3, "15": 19, "concluir\u00e3\u00a1": 14, "16": 14, "partir": 87, "marzo": 29, "1995": 4, "per\u00e3\u00adodos": 3, "ordinarias": 2, "celebrar\u00e3\u00a1n": 2, "acuerdo": 8, "fechas": 4, "nombramiento": 12, "cargo": 19, "jefe": 11, "t\u00e3\u00a9rminos": 75, "este": 108, "verificar\u00e3\u00a1": 2, "diciembre": 29, "constitucional": 37, "respectivo": 5, "a\u00e3\u00b1o": 71, "2000": 7, "tanto": 50, "dicho": 19, "asume": 1, "gobierno": 44, "seguir\u00e3\u00a1": 6, "presidente": 24, "rep\u00e3\u00bablica": 33, "1a": 1, "vigente": 21, "mantendr\u00e3\u00a1": 2, "facultad": 13, "nombrar": 2, "remover": 1, "libremente": 3, "titular": 17, "\u00e3\u00b3rgano": 17, "u": 9, "\u00e3\u00b3rganos": 39, "ejerciendo": 5, "conducente": 8, "consejos": 3, "ciudadanos": 5, "demarcaci\u00e3\u00b3n": 3, "territorial": 5, "e": 33, "instalar\u00e3\u00a1n": 1, "conforme": 81, "estatuto": 2, "leyes": 60, "respectivas": 13, "s\u00e3\u00a9ptimo-": 6, "servidores": 13, "p\u00e3\u00bablicos": 25, "readscriban": 1, "administraci\u00e3\u00b3n": 22, "p\u00e3\u00bablica": 49, "dependencias": 5, "conservar\u00e3\u00a1n": 4, "todos": 35, "derechos": 32, "laborales": 13, "octavo-": 8, "iniciativas": 1, "ingresos": 22, "decretos": 1, "presupuesto": 21, "egresos": 12, "ejercicios": 5, "1996": 5, "cuentas": 5, "p\u00e3\u00bablicas": 8, "ser\u00e3\u00a1n": 35, "enviados": 1, "cuenta": 22, "correspondiente": 17, "revisada": 1, "noveno-": 6, "expidan": 10, "coordinen": 2, "sistema": 35, "fiscal": 23, "entre": 46, "continuar\u00e3\u00a1n": 35, "aplic\u00e3\u00a1ndose": 6, "normas": 24, "sobre": 32, "materia": 116, "rijan": 2, "d\u00e3\u00a9cimo-": 2, "nuevas": 4, "aplicables": 31, "rigiendo": 3, "legales": 27, "reglamentarias": 3, "d\u00e3\u00a9cimo": 34, "conservar\u00e3\u00a1": 1, "legislar": 4, "\u00e3\u00a1mbito": 20, "local": 19, "materias": 9, "orden": 41, "com\u00e3\u00ban": 2, "civil": 9, "penal": 14, "ordenamientos": 12, "car\u00e3\u00a1cter": 12, "correspondientes": 25, "cuya": 2, "entrada": 145, "corresponder\u00e3\u00a1": 7, "particular": 6, "mediante": 23, "cual": 9, "declaran": 9, "reformados": 5, "diversos": 3, "22": 19, "agosto": 41, "siguiente": 117, "excepci\u00e3\u00b3n": 10, "previsto": 38, "adiciones": 11, "contenidas": 4, "ll": 1, "\u00e3\u00banicamente": 4, "refiere": 104, "legislaciones": 7, "electorales": 36, "calendarios": 1, "procesos": 18, "jornada": 1, "deba": 2, "celebrarse": 1, "antes": 27, "primero": 84, "abril": 25, "entrar\u00e3\u00a1n": 14, "enero": 24, "locales": 28, "motivo": 6, "\u00e3\u00banica": 9, "ocasi\u00e3\u00b3n": 3, "no": 122, "aplicar\u00e3\u00a1": 2, "plazo": 101, "se\u00e3\u00b1alado": 4, "cuarto": 77, "ii": 66, "acciones": 10, "inconstitucionalidad": 2, "tengan": 8, "objeto": 17, "plantear": 1, "posible": 6, "contradicci\u00e3\u00b3n": 1, "norma": 3, "ejerciten": 1, "previstos": 9, "misma": 26, "sujetar\u00e3\u00a1n": 5, "especiales:": 1, "a)": 48, "segundo": 172, "mencionado": 2, "acci\u00e3\u00b3n": 3, "quince": 2, "naturales;": 2, "b)": 40, "suprema": 7, "corte": 8, "justicia": 36, "naci\u00e3\u00b3n": 16, "deber\u00e3\u00a1": 93, "resolver": 8, "ejercida": 1, "mayor": 31, "h\u00e3\u00a1biles": 4, "contados": 18, "presentaci\u00e3\u00b3n": 7, "escrito": 1, "inicial": 11, "116": 18, "aplicar\u00e3\u00a1n": 4, "constitucionales": 10, "deban": 3, "celebrar": 3, "cuyo": 9, "inicio": 21, "haya": 11, "ocurrido": 1, "ocurra": 1, "estos": 10, "casos": 8, "dispondr\u00e3\u00a1n": 3, "contado": 17, "conclusi\u00e3\u00b3n": 7, "respectivos": 10, "adecuar": 8, "marco": 20, "legal": 7, "precepto": 2, "citado": 7, "dem\u00e3\u00a1s": 24, "encuentren": 24, "comprendidos": 1, "anterior": 69, "modificado": 2, "exceder\u00e3\u00a1": 5, "seis": 17, "meses": 18, "m\u00e3\u00a1s": 38, "tardar": 29, "estar": 6, "nombrados": 11, "consejero": 8, "consejo": 35, "instituto": 98, "ocho": 10, "nuevos": 11, "consejeros": 26, "suplentes": 4, "sustituir\u00e3\u00a1n": 1, "podr\u00e3\u00a1n": 38, "ser": 52, "reelectos": 1, "hacen": 6, "nombramientos": 12, "o": 165, "reforma": 120, "ley": 140, "competencias": 16, "actualmente": 9, "se\u00e3\u00b1ala": 3, "c\u00e3\u00b3digo": 4, "instituciones": 20, "procedimientos": 35, "quincuag\u00e3\u00a9sima": 1, "s\u00e3\u00a9ptima": 1, "principio": 5, "representaci\u00e3\u00b3n": 4, "proporcional": 3, "listas": 9, "votadas": 1, "sola": 4, "circunscripci\u00e3\u00b3n": 2, "plurinominal": 2, "nacional": 125, "se\u00e3\u00b1alada": 3, "asignaci\u00e3\u00b3n": 15, "f\u00e3\u00b3rmula": 5, "tome": 1, "cociente": 4, "natural": 10, "resto": 3, "mayor;": 1, "decreciente": 1, "tercero": 82, "mismo": 36, "reformaron": 2, "designarse": 1, "requerir\u00e3\u00a1n": 3, "voto": 10, "tres": 28, "cuartas": 1, "partes": 13, "miembros": 16, "presentes": 12, "expiden": 3, "elegir\u00e3\u00a1": 5, "ejercer\u00e3\u00a1": 10, "mandato": 14, "vez": 34, "hasta": 60, "4": 18, "determina": 2, "expedir": 22, "elecciones": 4, "inciso": 63, "f)": 13, "v": 42, "apartado": 83, "c": 22, "1998": 2, "requisito": 1, "segunda": 3, "proh\u00e3\u00adbe": 1, "acceder": 3, "si": 15, "hubiese": 1, "desempe\u00e3\u00b1ado": 2, "tal": 11, "cualquier": 24, "debe": 3, "entenderse": 2, "aplicable": 17, "todo": 10, "ciudadano": 2, "sido": 10, "aunque": 1, "bajo": 20, "distinta": 1, "tercera": 2, "titulares": 7, "pol\u00e3\u00adtico-administrativos": 2, "demarcaciones": 6, "territoriales": 6, "2000;": 1, "forma": 25, "indirecta": 2, "se\u00e3\u00b1ale": 7, "establece": 12, "legislativa": 19, "1999": 9, "jurisdicci\u00e3\u00b3n": 2, "inmuebles": 2, "sitos": 1, "est\u00e3\u00a9n": 8, "destinados": 4, "servicio": 18, "prestan": 2, "poderes": 14, "otro": 8, "bien": 5, "afecto": 2, "uso": 29, "dichos": 16, "regulan": 1, "seguir\u00e3\u00a1n": 8, "competentes": 8, "aquellos": 6, "sustituirlos": 1, "bases": 8, "se\u00e3\u00b1aladas": 3, "sal\u00e3\u0093n": 7, "comisi\u00e3\u0093n": 7, "honorable": 20, "uni\u00e3\u0093n-": 7, "21": 17, "1996-": 1, "fernando": 9, "ortiz": 4, "arana": 1, "martina": 1, "montenegro": 1, "espinoza": 1, "secretaria-": 66, "francisco": 38, "xavier": 6, "salazar": 5, "s\u00e3\u00a1enz": 5, "veinti\u00e3\u00ban": 3, "seis-": 5, "ernesto": 24, "zedillo": 12, "ponce": 13, "le\u00e3\u00b3n-": 12, "r\u00e3\u00babrica-": 95, "chuayffet": 2, "chemor-": 2, "30": 20, "32": 3, "37": 7, "20": 15, "hayan": 17, "perdido": 1, "nacionalidad": 4, "mexicana": 2, "nacimiento": 4, "haber": 2, "adquirido": 1, "voluntariamente": 1, "extranjera": 5, "encuentran": 2, "pleno": 8, "goce": 1, "beneficiarse": 1, "previa": 5, "solicitud": 5, "hagan": 8, "secretar\u00e3\u00ada": 28, "relaciones": 3, "exteriores": 1, "tiempo": 10, "reformado": 17, "dof": 6, "22-07-2004": 1, "anterioridad": 11, "nacidos": 1, "concebidos": 1, "durante": 16, "vigencia": 20, "aquello": 1, "les": 18, "favorezca": 1, "sin": 32, "perjuicio": 15, "beneficios": 2, "contenida": 1, "26-02-1999": 1, "emita": 3, "oponga": 4, "\u00e3\u00baltimo": 19, "c)": 45, "5": 14, "1997-": 1, "osorio": 28, "palacios": 1, "melquiades": 1, "morales": 9, "flores": 1, "armando": 1, "ballinas": 1, "mayes": 1, "siete": 7, "siete-": 10, "declara": 13, "3o": 14, "transitorio": 120, "26": 16, "febrero": 27, "art\u00e3\u008dculo": 70, "\u00e3\u009anico-": 68, "1999-": 7, "porfirio": 6, "mu\u00e3\u00b1oz": 11, "ledo": 3, "guadalupe": 7, "g\u00e3\u00b3mez": 13, "maganda": 1, "carlos": 22, "jim\u00e3\u00a9nez": 5, "mac\u00e3\u00adas": 1, "veintid\u00e3\u00b3s": 5, "nueve-": 13, "labastida": 1, "ochoa-": 1, "94": 4, "97": 4, "11": 9, "junio": 57, "judicatura": 8, "concluir\u00e3\u00a1n": 9, "senado": 20, "designar": 2, "conformidad": 25, "dentro": 68, "naturales": 44, "designados": 11, "vencer\u00e3\u00a1": 1, "2002": 5, "2004": 7, "2006;": 1, "2003": 3, "2007;": 1, "designado": 1, "2005": 10, "se\u00e3\u00b1alar": 1, "queda": 2, "instalado": 3, "antecede": 2, "funcionar\u00e3\u00a1": 2, "comisi\u00e3\u00b3n": 46, "temporal": 1, "compuesta": 1, "funcionarios": 2, "dependan": 1, "directamente": 2, "propio": 5, "dicha": 18, "proveer\u00e3\u00a1": 3, "tr\u00e3\u00a1mites": 4, "resolver\u00e3\u00a1": 2, "asuntos": 13, "administrativos": 3, "notoria": 1, "urgencia": 1, "presenten": 2, "relacionados": 9, "adscripci\u00e3\u00b3n": 1, "ratificaci\u00e3\u00b3n": 4, "remoci\u00e3\u00b3n": 2, "jueces": 6, "dar\u00e3\u00a1": 5, "medidas": 15, "tomadas": 1, "fin": 24, "\u00e3\u00a9ste": 8, "acuerde": 1, "proceda": 3, "aluden": 1, "iniciados": 14, "tramit\u00e3\u00a1ndose": 2, "fueron": 10, "9": 15, "mar\u00e3\u00ada": 28, "angeles": 7, "moreno": 10, "uriegas": 7, "presidenta-": 10, "m\u00e3\u00b3nica": 4, "garc\u00e3\u00ada": 7, "vel\u00e3\u00a1zquez": 3, "diez": 18, "di\u00e3\u00b3doro": 9, "carrasco": 9, "altamirano-": 9, "xxix-j": 4, "28": 15, "fija": 1, "m\u00e3\u00a1ximo": 26, "expedici\u00e3\u00b3n": 7, "reglamentaria": 19, "atribuciones": 32, "deporte": 2, "ma": 4, "veintitr\u00e3\u00a9s": 4, "58": 1, "29": 10, "julio": 40, "14": 12, "camarena": 3, "castro": 4, "veintisiete": 4, "78": 8, "fiscalizaci\u00e3\u00b3n": 14, "superior": 16, "iniciar\u00e3\u00a1": 6, "1": 16, "revisi\u00e3\u00b3n": 11, "refieren": 6, "fracciones": 49, "iv": 51, "llevar\u00e3\u00a1n": 3, "cabo": 20, "2001": 3, "revisar\u00e3\u00a1": 3, "a\u00e3\u00b1os": 23, "referencias": 3, "dichas": 15, "contadur\u00e3\u00ada": 4, "hacienda": 14, "entender\u00e3\u00a1n": 3, "hechas": 2, "empiece": 1, "ejercer": 5, "tiene": 1, "org\u00e3\u00a1nica": 7, "jur\u00e3\u00addicas": 2, "afectados": 8, "alguna": 5, "consecuencia": 6, "emitan": 3, "creada": 1, "recursos": 69, "humanos": 15, "materiales": 17, "patrimoniales": 1, "pasar\u00e3\u00a1n": 6, "formar": 11, "parte": 13, "contador": 1, "2001;": 1, "podr\u00e3\u00a1": 35, "ratificado": 1, "continuar": 3, "completar": 1, "constituci\u00e3\u00b3n\"": 1, "adiciona": 60, "102": 8, "b": 27, "13": 11, "integrantes": 22, "consultivo": 2, "concluir": 4, "pudiendo": 1, "caso": 65, "propuestos": 1, "elegidos": 2, "sesenta": 22, "elegir": 4, "procedimiento": 11, "efecto": 33, "observar\u00e3\u00a1n": 2, "reglas:": 1, "a-": 1, "proceder\u00e3\u00a1": 4, "realizar": 34, "amplia": 1, "auscultaci\u00e3\u00b3n": 2, "organizaciones": 4, "sociales": 4, "representativas": 1, "distintos": 3, "sectores": 3, "sociedad": 3, "organismos": 18, "privados": 1, "promotores": 1, "defensores": 2, "b-": 1, "proponer": 2, "actual": 17, "terna": 7, "expide": 7, "\u00e3\u00a9sta": 7, "18": 17, "adicionado": 8, "115": 7, "23": 5, "constituciones": 7, "adecuaciones": 34, "realizan": 1, "aplicando": 2, "trat\u00e3\u00a1ndose": 4, "servicios": 50, "sean": 12, "competencia": 29, "municipios": 14, "prestados": 1, "gobiernos": 5, "estatales": 11, "manera": 16, "coordinada": 1, "\u00e3\u00a9stos": 7, "asumirlos": 1, "aprobaci\u00e3\u00b3n": 18, "ayuntamiento": 2, "necesario": 8, "funci\u00e3\u00b3n": 11, "p\u00e3\u00bablico": 27, "trate": 10, "transfiera": 2, "municipio": 2, "ordenada": 1, "programa": 14, "transferencia": 7, "90": 9, "recepci\u00e3\u00b3n": 2, "solicitar": 4, "conservar": 1, "cuando": 25, "afecte": 2, "prestaci\u00e3\u00b3n": 9, "estatal": 1, "realiza": 2, "ejerci\u00e3\u00a9ndose": 1, "prest\u00e3\u00a1ndose": 1, "condiciones": 23, "realizar\u00e3\u00a1n": 8, "actos": 9, "conducentes": 8, "convenios": 4, "hubiesen": 1, "celebrado": 1, "ajusten": 2, "establecido": 19, "coordinaci\u00e3\u00b3n": 13, "adoptar\u00e3\u00a1n": 4, "valores": 3, "unitarios": 1, "suelo": 1, "sirven": 1, "cobro": 3, "contribuciones": 6, "propiedad": 4, "inmobiliaria": 1, "equiparables": 1, "mercado": 6, "proceder\u00e3\u00a1n": 1, "tasas": 1, "mencionadas": 2, "garantizar": 12, "apego": 1, "principios": 19, "proporcionalidad": 2, "equidad": 3, "realizaci\u00e3\u00b3n": 6, "respetar\u00e3\u00a1n": 5, "obligaciones": 23, "contra\u00e3\u00addos": 1, "previamente": 3, "terceros": 3, "trabajadores": 21, "municipales": 6, "crist\u00e3\u00b3bal": 1, "arias": 2, "sol\u00e3\u00ads": 1, "paoli": 2, "bolio": 2, "alejandro": 8, "acevedo": 1, "j": 1, "loyo": 1, "ramos": 7, "4o": 12, "7": 13, "8": 14, "2000-": 3, "sergio": 2, "vald\u00e3\u00a9s": 1, "miguel": 34, "quiroz": 1, "p\u00e3\u00a9rez": 3, "mil-": 3, "reformadas": 5, "adicionadas": 4, "derogadas": 3, "diversas": 19, "jes\u00e3\u00bas": 44, "padilla": 4, "angelina": 3, "fern\u00e3\u00a1ndez": 7, "diecinueve": 2, "reformada": 1, "xxv": 6, "aprueba": 7, "diverso": 7, "adicionan": 40, "tercer": 25, "p\u00e3\u00a1rrafos": 89, "2o": 5, "4o;": 3, "sexto": 43, "estas": 6, "entidades": 49, "federativas": 44, "procedan": 2, "reglamenten": 2, "aqu\u00e3\u00ad": 1, "estipulado": 2, "establecer": 25, "tomarse": 1, "consideraci\u00e3\u00b3n": 5, "sea": 22, "factible": 1, "ubicaci\u00e3\u00b3n": 2, "pueblos": 2, "comunidades": 4, "ind\u00e3\u00adgenas": 3, "propiciar": 2, "participaci\u00e3\u00b3n": 7, "dispondr\u00e3\u00a1": 2, "texto": 2, "\u00e3\u00adntegro": 1, "exposici\u00e3\u00b3n": 1, "motivos": 1, "cuerpo": 2, "normativo": 1, "traduzca": 1, "lenguas": 1, "ordenar\u00e3\u00a1": 1, "difusi\u00e3\u00b3n": 4, "2001-": 1, "fidel": 2, "herrera": 1, "beltr\u00e3\u00a1n": 1, "vicepresidente": 1, "susana": 3, "sthepenson": 1, "uno-": 1, "vicente": 17, "fox": 17, "quesada-": 17, "santiago": 14, "creel": 14, "miranda-": 8, "modifica": 4, "113": 3, "contar\u00e3\u00a1n": 2, "periodo": 18, "comprendido": 3, "modificaciones": 8, "necesarias": 29, "proveer": 5, "debido": 4, "incluir": 4, "presupuestos": 10, "partida": 1, "hacer": 6, "frente": 1, "responsabilidad": 4, "patrimonial": 2, "implicar\u00e3\u00a1": 1, "necesariamente": 1, "adecuaci\u00e3\u00b3n": 1, "secundarias": 3, "criterios": 7, "siguientes:": 8, "pago": 7, "indemnizaci\u00e3\u00b3n": 4, "efectuar\u00e3\u00ada": 1, "seguir": 2, "determinar": 16, "efectivamente": 1, "corresponde": 2, "estar\u00e3\u00a1": 10, "sujeto": 5, "disponibilidad": 2, "presupuestaria": 4, "contar\u00e3\u00ada": 1, "consiguiente": 1, "ser\u00e3\u00ada": 1, "menor": 2, "ni": 17, "mayo": 28, "2002-": 2, "diego": 3, "cevallos": 3, "manuel": 5, "a\u00e3\u00b1orve": 2, "ba\u00e3\u00b1os": 2, "trece": 4, "dos-": 2, "12": 12, "autoridad": 12, "educativa": 5, "instalar": 3, "comisiones": 13, "t\u00e3\u00a9cnicas": 6, "consulta": 2, "autoridades": 21, "educativas": 3, "resulten": 8, "pertinentes": 5, "iniciar": 4, "tendiente": 2, "unificaci\u00e3\u00b3n": 1, "estructural": 3, "curricular": 1, "laboral": 2, "niveles": 3, "obligatorios": 1, "solo": 2, "nivel": 6, "educaci\u00e3\u00b3n": 22, "b\u00e3\u00a1sica": 2, "integrada": 2, "planes": 3, "programas": 10, "estudio": 4, "preescolar": 9, "obligatoria": 3, "preparar": 1, "personal": 7, "docente": 4, "directivo": 3, "realidad": 1, "surge": 1, "objetivo": 3, "impulsar": 2, "calidad": 11, "prever": 7, "dar": 11, "dispone": 1, "5o": 2, "profesiones": 1, "sentido": 3, "impartici\u00e3\u00b3n": 1, "es": 4, "profesi\u00e3\u00b3n": 1, "necesita": 1, "adquiridos": 2, "imparten": 1, "educativo": 5, "plazos:": 1, "ciclo": 5, "2004-2005;": 1, "2005-2006;": 1, "2008-2009": 1, "plazos": 9, "se\u00e3\u00b1alados": 4, "mexicano": 11, "habr\u00e3\u00a1": 1, "universalizar": 1, "oferta": 2, "incluir\u00e3\u00a1n": 5, "necesarios": 22, "para:": 3, "construcci\u00e3\u00b3n": 3, "ampliaci\u00e3\u00b3n": 2, "equipamiento": 1, "infraestructura": 12, "suficiente": 1, "cobertura": 16, "progresiva": 1, "preescolar;": 1, "formaci\u00e3\u00b3n": 4, "profesional": 8, "dotaci\u00e3\u00b3n": 1, "gratuito": 1, "maestros": 5, "alumnos": 4, "rurales": 1, "alejadas": 1, "centros": 4, "urbanos": 1, "zonas": 1, "donde": 3, "establecer\u00e3\u00a1n": 5, "especiales": 3, "requieran": 5, "tomar\u00e3\u00a1n": 2, "decisiones": 1, "asegurar": 12, "acceso": 33, "educandos": 2, "primaria": 1, "colaboraci\u00e3\u00b3n": 3, "permitan": 5, "cumplir": 15, "obligatoriedad": 3, "establecidos": 7, "anteriores": 12, "impulsarse": 2, "xxix-m": 1, "2004-": 5, "enrique": 43, "jackson": 11, "ram\u00e3\u00adrez": 22, "dios": 1, "lozano": 1, "sara": 3, "castellanos": 5, "cort\u00e3\u00a9s": 6, "marcos": 2, "torres": 3, "cuatro-": 5, "veinte": 9, "jorge": 6, "uscanga": 2, "escobar": 2, "r\u00e3\u00babricas\u00e2\u0080\u009d": 6, "cruz": 6, "l\u00e3\u00b3pez": 13, "aguilar": 5, "veintiocho": 4, "65": 1, "xxix-l": 2, "27": 23, "unico": 1, "quedar": 94, "sigue:": 90, "": 33, "recorri\u00e3\u00a9ndose": 28, "pasan": 3, "s\u00e3\u00a9ptimo": 27, "2005-": 5, "su\u00e3\u00a1rez": 1, "diecisiete": 2, "cinco-": 5, "abascal": 9, "carranza-": 9, "xxi": 22, "\u00e3\u009anico": 35, "heliodoro": 4, "d\u00e3\u00adaz": 5, "esc\u00e3\u00a1rraga": 4, "patricia": 3, "gardu\u00e3\u00b1o": 3, "yolanda": 4, "hern\u00e3\u00a1ndez": 7, "\u00e3\u00banico": 3, "46;": 2, "73;": 8, "x": 10, "xi": 8, "pasando": 8, "xii": 3, "46": 2, "establecer\u00e3\u00a1": 26, "ordinario": 2, "inmediato": 6, "l\u00e3\u00admites": 4, "expida": 13, "dispongan": 1, "reglamento": 7, "interior": 6, "controversias": 6, "tr\u00e3\u00a1mite": 12, "ante": 10, "conflictos": 4, "lim\u00e3\u00adtrofes": 1, "remitidas": 1, "antecedentes": 1, "establecerlos": 1, "definitiva": 1, "legislativo": 6, "derogado": 1, "adicionados": 3, "recorre": 7, "\u00e3\u00baltimos": 6, "crear": 4, "aplicaci\u00e3\u00b3n": 6, "contar\u00e3\u00a1": 8, "implementaci\u00e3\u00b3n": 5, "integral": 3, "adolescentes": 6, "14-08-2009": 2, "entren": 8, "implementen": 1, "legislaci\u00e3\u00b3n": 48, "iniciaron": 1, "pendientes": 5, "resoluci\u00e3\u00b3n": 9, "inicie": 7, "operaci\u00e3\u00b3n": 15, "nuevo": 21, "remitir\u00e3\u00a1n": 1, "resulte": 6, "competente": 5, "contin\u00e3\u00bae": 5, "conocimiento": 1, "rocha": 2, "medina": 2, "xxix-d": 2, "2006": 6, "informaci\u00e3\u00b3n": 35, "estad\u00e3\u00adstica": 5, "geogr\u00e3\u00a1fica": 4, "administrativas": 5, "asimismo": 19, "subsistir\u00e3\u00a1n": 1, "mandatos": 4, "delegaciones": 1, "concedidas": 1, "geograf\u00e3\u00ada": 4, "inform\u00e3\u00a1tica": 3, "financieros": 16, "adscritos": 4, "desconcentrado": 2, "cr\u00e3\u00a9dito": 6, "transferir\u00e3\u00a1n": 2, "organismo": 35, "creado": 6, "pasen": 2, "123": 12, "ninguna": 6, "resultar\u00e3\u00a1n": 3, "seguridad": 26, "social": 15, "r\u00e3\u00a9gimen": 10, "presupuestario": 3, "libre": 4, "no-transferencia": 1, "suficiencia": 3, "est\u00e3\u00a9": 2, "formule": 1, "substanciando": 2, "posteriormente": 1, "180": 16, "posteriores": 11, "emitir": 4, "aquellas": 6, "2006-": 4, "marcela": 1, "salas": 2, "p": 1, "sa\u00e3\u00bal": 2, "sollano": 1, "g)": 8, "diva": 1, "hadamira": 1, "gastelum": 1, "once": 1, "xxix-h": 8, "modifique": 1, "regula": 2, "responsabilidades": 10, "rigi\u00e3\u00a9ndose": 1, "zerme\u00e3\u00b1o": 3, "infante": 3, "manlio": 16, "fabio": 16, "beltrones": 16, "rivera": 18, "lilia": 4, "gpe": 1, "merodio": 4, "reza": 5, "ludivina": 3, "menchaca": 3, "mercedez": 1, "maciel": 1, "2007": 11, "i;": 1, "17": 18, "2007-": 9, "angel": 2, "pe\u00e3\u00b1a": 29, "sanchez": 2, "ricardo": 7, "pacheco": 1, "rodriguez": 1, "felipe": 36, "calder\u00e3\u00b3n": 36, "hinojosa-": 36, "javier": 19, "acu\u00e3\u00b1a-": 9, "82": 4, "19": 9, "navarro": 5, "doce": 11, "55": 3, "contenido": 9, "normativas": 4, "complemento": 1, "prevenci\u00e3\u00b3n": 1, "accidentes": 1, "protecci\u00e3\u00b3n": 12, "siempre": 11, "sujeten": 1, "establezca": 17, "diecis\u00e3\u00a9is": 7, "6o": 20, "\u00e3\u00a1mbitos": 1, "transparencia": 16, "contar": 4, "sistemas": 5, "electr\u00e3\u00b3nicos": 4, "persona": 6, "pueda": 6, "remoto": 1, "mecanismos": 24, "setenta": 1, "habitantes": 1, "cuenten": 11, "orozco": 5, "dieciocho": 3, "92": 2, "93": 5, "95": 3, "110": 5, "111": 5, "numeral": 8, "xvi": 2, "primeros": 5, "s\u00e3\u0089ptimo-": 5, "xxix-n": 2, "99": 4, "veinticuatro": 4, "85": 2, "108": 7, "122;": 6, "134": 7, "6o;": 4, "99;": 4, "85;": 2, "108;": 2, "116;": 6, "finales": 2, "134;": 1, "tope": 1, "gastos": 3, "campa\u00e3\u00b1a": 2, "presidencial": 2, "2008": 12, "s\u00e3\u00b3lo": 11, "monto": 10, "total": 11, "financiamiento": 8, "privado": 2, "obtener": 3, "anualmente": 2, "partido": 3, "pol\u00e3\u00adtico": 3, "correspondan": 14, "efectos": 14, "bases:": 1, "2013;": 1, "llegado": 1, "nombrado": 3, "reelecto": 1, "constituci\u00e3\u00b3n;": 2, "2016": 13, "2010;": 1, "d)": 22, "2013": 12, "da": 1, "renovaci\u00e3\u00b3n": 6, "escalonada": 7, "sala": 1, "regionales": 1, "judicial": 12, "determine": 6, "vigor;": 1, "observar\u00e3\u00a1": 2, "iniciado": 1, "iniciarlos": 1, "comicios": 2, "establezcan": 11, "pero": 2, "terminado": 1, "comicial": 1, "6": 9, "ruth": 2, "zavaleta": 2, "salgado": 3, "miranda": 6, "adame": 2, "adrian": 1, "octavo": 25, "p\u00e3\u00a1rrafos;": 2, "p\u00e3\u00a1rrafo;": 5, "incisos": 15, "e)": 13, "xxviii;": 1, "vi;": 5, "respectivamente": 8, "quinto;": 6, "noveno": 14, "\u00e2\u0080\u00a6\u00e2\u0080\u00a6\u00e2\u0080\u00a6": 57, "aprobar": 7, "informe": 6, "resultado": 5, "siguiente:": 18, "fiscales": 4, "revisadas": 1, "presentada": 2, "2009": 10, "2008-": 5, "gabino": 5, "cue": 4, "monteagudo": 5, "esmeralda": 4, "cardenas": 1, "ocho-": 5, "camilo": 5, "mouri\u00e3\u00b1o": 5, "terrazo-": 5, "22;": 1, "xxiii": 3, "vii": 14, "xiii": 5, "procesal": 11, "acusatorio": 8, "decimotercero;": 3, "sexto;": 6, "19;": 2, "secundaria": 6, "exceder": 4, "poner": 1, "incorporar": 2, "modalidad": 2, "determinen": 5, "regional": 3, "tipo": 6, "delito": 3, "publiquen": 1, "legislativos": 1, "declaratoria": 6, "publicar\u00e3\u00a1": 2, "oficiales": 1, "expresamente": 2, "ha": 4, "incorporado": 2, "garant\u00e3\u00adas": 4, "consagra": 1, "empezar\u00e3\u00a1n": 1, "regular": 11, "substanciar\u00e3\u00a1n": 1, "penales": 8, "obstante": 1, "ya": 4, "hubieren": 7, "siendo": 2, "plenamente": 1, "v\u00e3\u00a1lidas": 1, "actuaciones": 1, "procesales": 2, "practicado": 1, "fundamento": 8, "tales": 7, "independientemente": 1, "entraron": 1, "prevista": 2, "concluidos": 3, "acto": 1, "reinserci\u00e3\u00b3n": 1, "modificaci\u00e3\u00b3n": 2, "duraci\u00e3\u00b3n": 1, "penas": 4, "delincuencia": 1, "organizada": 1, "ejerza": 3, "conferida": 2, "sentencias": 7, "emitidas": 7, "mismas": 11, "concluirse": 7, "ejecutarse": 7, "expedir\u00e3\u00a1": 11, "expedir\u00e3\u00a1n": 1, "destinar": 3, "partidas": 2, "presupuestales": 10, "se\u00e3\u00b1alarse": 2, "sucesivos": 1, "destinarse": 1, "dise\u00e3\u00b1o": 4, "cambios": 1, "organizacionales": 1, "capacitaci\u00e3\u00b3n": 5, "agentes": 7, "ministerio": 2, "polic\u00e3\u00adas": 3, "peritos": 1, "abogados": 1, "crear\u00e3\u00a1": 2, "instancia": 6, "adem\u00e3\u00a1s": 1, "sector": 7, "acad\u00e3\u00a9mico": 2, "conferencias": 1, "procuraci\u00e3\u00b3n": 1, "presidentes": 2, "tribunales": 10, "t\u00e3\u00a9cnica": 12, "coadyuvar\u00e3\u00a1": 1, "apoyar\u00e3\u00a1": 1, "soliciten": 6, "fondo": 22, "especial": 5, "actividades": 21, "fondos": 5, "otorgar\u00e3\u00a1n": 1, "fines": 1, "entra": 2, "juez": 2, "arraigo": 1, "domiciliario": 1, "indiciado": 3, "delitos": 5, "graves": 3, "cuarenta": 3, "medida": 19, "procedente": 1, "necesaria": 5, "\u00e3\u00a9xito": 2, "investigaci\u00e3\u00b3n": 3, "personas": 8, "bienes": 3, "jur\u00e3\u00addicos": 4, "exista": 4, "riesgo": 2, "fundado": 1, "inculpado": 1, "sustraiga": 1, "monreal": 2, "\u00e3\u0081vila": 2, "69": 4, "69;": 2, "ambos": 6, "contravengan": 6, "88": 2, "oralia": 2, "veintis\u00e3\u00a9is": 4, "xxix-\u00e3\u0091": 3, "emitidos": 5, "fundamentados": 2, "derecho": 20, "autor": 1, "registros": 4, "obras": 2, "contratos": 31, "reservas": 1, "otorgadas": 1, "resoluciones": 8, "otros": 12, "celebrados": 2, "particulares": 15, "sucesiones": 1, "testamentarias": 1, "validez": 1, "24": 10, "2009-": 6, "gustavo": 6, "madero": 6, "c\u00e3\u00a9sar": 4, "horacio": 4, "duarte": 4, "j\u00e3\u00a1quez": 3, "portilla": 1, "dieguez": 1, "lic": 8, "mont": 8, "urueta-": 8, "xxix-o": 2, "respectiva": 6, "dictado": 1, "datos": 19, "personales": 8, "posesi\u00e3\u00b3n": 4, "d": 4, "f": 3, "eugenia": 1, "valenzuela": 1, "secuestro": 1, "margarita": 2, "arenas": 2, "guzman": 2, "subsecuentes": 14, "cesar": 1, "jaquez": 1, "cu\u00e3\u00a9": 1, "fe": 1, "errata": 1, "publicada": 4, "secci\u00e3\u00b3n": 1, "p\u00e3\u00a1gina": 1, "transcrito": 1, "dice:": 1, "librarse": 2, "aprehensi\u00e3\u00b3n": 2, "sino": 3, "denuncia": 3, "querella": 2, "hecho": 5, "sancionado": 3, "pena": 2, "privativa": 2, "libertad": 5, "obren": 2, "cometido": 4, "ese": 4, "probabilidad": 2, "cometi\u00e3\u00b3": 2, "particip\u00e3\u00b3": 2, "decir:": 1, "preceda": 1, "c\u00e3\u00a1rdenas": 2, "s\u00e3\u00a1nchez": 6, "75": 1, "127": 6, "115;": 2, "123;": 3, "75;": 1, "quedar\u00e3\u00a1n": 4, "remuneraciones": 3, "superiores": 4, "m\u00e3\u00a1xima": 5, "establecida": 3, "ajustadas": 1, "disminuidas": 1, "aqu\u00e3\u00a9l": 3, "entrado": 3, "percepciones": 1, "ministros": 1, "circuito": 3, "judiciales": 1, "retribuciones": 2, "nominales": 3, "mantendr\u00e3\u00a1n": 1, "dure": 1, "adicionales": 6, "gratificaciones": 1, "premios": 1, "recompensas": 1, "bonos": 1, "est\u00e3\u00admulos": 1, "compensaciones": 1, "remuneraci\u00e3\u00b3n": 4, "dinero": 1, "especie": 1, "mantener": 1, "exceda": 1, "incrementos": 1, "realizarse": 3, "excede": 1, "referido": 11, "tipificar": 1, "sancionar": 4, "administrativamente": 1, "conductas": 1, "finalidad": 4, "eludir": 1, "veintiuno": 4, "cuarta": 2, "2010": 2, "2010-": 2, "navarrete": 3, "ruiz": 6, "acu\u00e3\u00b1a": 1, "jaime": 2, "arturo": 4, "v\u00e3\u00a1zquez": 3, "diez-": 2, "legislativas": 4, "\u00e3\u0093scar": 1, "castillo": 1, "andrade": 8, "43": 2, "2011": 8, "2011-": 8, "ramirez": 1, "marin": 1, "samuel": 1, "teran": 1, "martha": 1, "leticia": 1, "sosa": 1, "govea": 1, "once-": 8, "103": 3, "modificar": 3, "ubicado": 1, "lugar;": 1, "incorpora": 2, "lugar": 5, "manera:": 2, "inicial;": 1, "ii;": 4, "iii;": 6, "vii;": 5, "viii;": 4, "xiv": 1, "120": 3, "juicios": 2, "amparo": 6, "final": 2, "relativas": 11, "sobreseimiento": 1, "inactividad": 1, "caducidad": 1, "ejecuci\u00e3\u00b3n": 11, "integraci\u00e3\u00b3n": 16, "jurisprudencia": 1, "reiteraci\u00e3\u00b3n": 1, "tesis": 1, "aprobadas": 1, "resueltos": 3, "blake": 7, "mora-": 7, "cap\u00e3\u00adtulo": 2, "10": 7, "primero;": 12, "1o;": 1, "3o;": 1, "11;": 1, "15;": 1, "18;": 1, "29;": 3, "33;": 1, "d\u00e3\u00a9cima": 1, "89;": 5, "97;": 1, "102;": 2, "105;": 4, "orden;": 4, "33": 2, "b;": 1, "reparaci\u00e3\u00b3n": 1, "expedida": 5, "asilo": 1, "suspensi\u00e3\u00b3n": 3, "expulsi\u00e3\u00b3n": 1, "extranjeros": 1, "referida": 4, "desahogando": 1, "autonom\u00e3\u00ada": 12, "adecuar\u00e3\u00a1": 1, "nueve": 4, "prevenir": 2, "trata": 1, "zamora": 3, "71": 3, "72": 2, "arroyo": 9, "vieyra": 2, "vicepresidente-": 1, "cultura": 1, "f\u00e3\u00adsica": 3, "xxix-p": 3, "claudia": 1, "massieu": 1, "salinas": 1, "xx": 3, "2012": 9, "medio": 9, "ambiente": 6, "sano": 1, "da\u00e3\u00b1o": 1, "deterioro": 1, "ambiental": 2, "360": 1, "aguas": 1, "2012-": 6, "acosta": 2, "naranjo": 2, "rigoberto": 1, "ren\u00e3\u00a1n": 1, "cleominio": 1, "zoreda": 1, "novelo": 1, "doce-": 6, "alfonso": 7, "poir\u00e3\u00a9": 6, "romero-": 6, "art\u00e3\u008dculos": 3, "media": 2, "deber": 1, "ofrecer": 3, "cursarla": 1, "quien": 6, "edad": 2, "t\u00e3\u00adpica": 1, "hubiera": 2, "concluido": 5, "gradual": 1, "creciente": 1, "escolar": 2, "2012-2013": 1, "lograr": 3, "modalidades": 9, "2021-2022": 1, "concurrencia": 3, "presupuestal": 3, "instrumentos": 5, "planeaci\u00e3\u00b3n": 3, "democr\u00e3\u00a1tica": 3, "desarrollo": 32, "necesarios;": 1, "plurianuales": 1, "aseguren": 2, "largo": 16, "econ\u00e3\u00b3micos": 6, "crecientes": 1, "merino": 1, "luis": 2, "alberto": 1, "villarreal": 1, "atracci\u00e3\u00b3n": 2, "morf\u00e3\u00adn": 3, "gloria": 2, "romero": 1, "le\u00e3\u00b3n": 1, "reforman:": 1, "35;": 4, "36;": 1, "71;": 2, "xxvi": 1, "74;": 3, "76;": 4, "78;": 1, "83;": 2, "(que": 1, "quinto)": 1, "84;": 4, "adicionan:": 1, "viii": 18, "xxix-q": 1, "87;": 1, "o)": 4, "subsecuente": 3, "articulo": 1, "contando": 1, "congresos": 1, "derivadas": 4, "aguirre": 1, "maldonado": 1, "suprimen": 1, "correa": 1, "40": 1, "cordero": 9, "murillo": 1, "karam": 1, "rosa": 3, "adriana": 2, "diaz": 1, "lizama": 2, "cedillo": 1, "veintinueve": 2, "xxv;": 1, "someter\u00e3\u00a1": 6, "ternas": 3, "designaci\u00e3\u00b3n": 11, "junta": 14, "evaluaci\u00e3\u00b3n": 20, "recaer": 1, "capacidad": 5, "experiencia": 1, "periodos": 5, "a\u00e3\u00b1os;": 3, "corresponda": 7, "someter": 3, "conformaci\u00e3\u00b3n": 4, "ellas": 3, "designen": 1, "constituir\u00e3\u00a1n": 1, "futuro": 1, "precisa": 1, "durar\u00e3\u00a1": 2, "cuatro": 8, "crea": 8, "previstas": 12, "ordenamiento": 3, "\u00e3\u0093rgano": 1, "ejercidas": 1, "presidencia": 1, "descentralizado": 10, "menos": 25, "creaci\u00e3\u00b3n": 8, "gesti\u00e3\u00b3n": 7, "escuelas": 5, "permita": 7, "tener": 5, "plataforma": 5, "comunicaci\u00e3\u00b3n": 8, "directa": 8, "directores": 2, "escuela": 2, "educativas;": 1, "desempe\u00e3\u00b1o": 6, "pertinencia": 1, "capacidades": 5, "actualizaci\u00e3\u00b3n": 16, "superaci\u00e3\u00b3n": 1, "prop\u00e3\u00b3sito": 1, "ellos": 1, "referentes": 1, "reflexi\u00e3\u00b3n": 1, "di\u00e3\u00a1logo": 1, "mejor": 3, "pr\u00e3\u00a1ctica": 1, "otorgar": 1, "apoyos": 1, "docentes": 1, "puedan": 10, "prioritariamente": 1, "desarrollar": 1, "fortalezas": 1, "superar": 1, "debilidades": 1, "jur\u00e3\u00addico": 23, "fortalecer": 1, "\u00e3\u00b3rdenes": 2, "mejorar": 1, "comprar": 1, "educativos": 1, "problemas": 1, "b\u00e3\u00a1sicos": 2, "padres": 1, "familia": 1, "liderazgo": 1, "director": 2, "involucren": 1, "retos": 1, "enfrenta": 1, "paulatina": 1, "completo": 1, "jornadas": 1, "horas": 1, "diarias": 1, "aprovechar": 1, "disponible": 2, "deportivo": 1, "cultural": 1, "necesiten": 1, "\u00e3\u00adndices": 1, "pobreza": 1, "marginaci\u00e3\u00b3n": 1, "condici\u00e3\u00b3n": 1, "alimentaria": 1, "impulsar\u00e3\u00a1n": 1, "esquemas": 2, "eficientes": 1, "suministro": 1, "alimentos": 2, "nutritivos": 1, "microempresas": 1, "prohibir": 1, "favorezcan": 1, "salud": 2, "prever\u00e3\u00a1": 7, "elementos": 9, "instrumentar": 1, "instrumentar\u00e3\u00a1": 1, "2013-": 9, "veinticinco": 3, "trece-": 9, "nieto-": 28, "\u00e3\u0081ngel": 27, "chong-": 27, "cristina": 7, "7o": 3, "telecomunicaciones": 56, "7o;": 1, "27;": 3, "28;": 4, "94;": 1, "decimotercero": 1, "trig\u00e3\u00a9simo": 1, "l)": 4, "fomento": 2, "televisi\u00e3\u00b3n": 18, "radio": 5, "telefon\u00e3\u00ada": 2, "aplicarse": 2, "segmentos": 1, "garantice": 1, "conjunto": 2, "efectiva": 6, "radiodifusi\u00e3\u00b3n": 18, "ciento": 36, "ochenta": 11, "deber\u00e3\u00a1:": 1, "tipos": 2, "castiguen": 1, "severamente": 2, "pr\u00e3\u00a1cticas": 4, "monop\u00e3\u00b3licas": 1, "fen\u00e3\u00b3menos": 1, "concentraci\u00e3\u00b3n;": 1, "virtud": 13, "denominado": 4, "promotor": 1, "medios": 10, "audiovisuales;": 1, "homologar": 1, "permisos": 5, "concesiones": 9, "existan": 5, "asegurando": 2, "diversidad": 1, "distinguir": 1, "comercial": 2, "incluyen": 1, "comunitarias": 1, "ind\u00e3\u00adgenas;": 1, "r\u00e3\u00a9plica;": 1, "prohibici\u00e3\u00b3n": 2, "difundir": 2, "publicidad": 7, "enga\u00e3\u00b1osa": 1, "subrepticia;": 1, "promoci\u00e3\u00b3n": 2, "producci\u00e3\u00b3n": 8, "independiente;": 1, "prohibiciones": 1, "espec\u00e3\u00adficas": 1, "subsidios": 2, "cruzados": 1, "trato": 1, "preferencial": 1, "consistentes": 2, "operadores": 4, "otorguen": 3, "proporcionan": 1, "s\u00e3\u00ad": 1, "trav\u00e3\u00a9s": 13, "empresas": 16, "subsidiarias": 1, "filiales": 1, "afiliadas": 1, "pertenezcan": 1, "grupo": 1, "inter\u00e3\u00a9s": 4, "econ\u00e3\u00b3mico": 10, "concesionario": 2, "fijar": 1, "tarifas": 4, "m\u00e3\u00adnimas": 1, "emisi\u00e3\u00b3n": 3, "anuncios": 1, "cuales": 8, "presentadas": 2, "registro": 28, "p\u00e3\u00bablico;": 1, "otorgar\u00e3\u00a1": 1, "autorizaciones": 3, "multiprogramaci\u00e3\u00b3n": 1, "garantizado": 1, "atendiendo": 7, "concentraci\u00e3\u00b3n": 1, "frecuencias": 4, "incluyendo": 10, "contraprestaciones": 9, "debidas;": 1, "integrado": 6, "honorarios": 1, "encargado": 5, "fungir": 1, "asesor": 1, "deriven": 2, "regule": 3, "convergente": 1, "aprovechamiento": 8, "explotaci\u00e3\u00b3n": 4, "espectro": 6, "radioel\u00e3\u00a9ctrico": 5, "redes": 8, "\u00e3\u00banicas": 1, "concesionarios": 18, "prestar": 4, "cumplan": 2, "imponga": 1, "determinado": 1, "tienen": 2, "agente": 8, "preponderante": 5, "lineamientos": 10, "requisitos": 4, "autorice": 1, "son": 4, "concesi\u00e3\u00b3n": 9, "transitar": 1, "modelo": 2, "t\u00e3\u00adtulos": 4, "autorizaci\u00e3\u00b3n": 4, "otorgarse": 1, "preponderantes": 4, "impuesto": 1, "procedencia": 1, "improcedencia": 1, "solicitudes": 1, "determinar\u00e3\u00a1": 6, "permitir\u00e3\u00a1": 2, "inversi\u00e3\u00b3n": 12, "cien": 2, "v\u00e3\u00ada": 6, "sat\u00e3\u00a9lite": 3, "reciprocidad": 1, "encuentre": 6, "constituido": 4, "inversionista": 1, "controle": 1, "indirectamente": 3, "transici\u00e3\u00b3n": 7, "digital": 8, "terrestre": 4, "culminar\u00e3\u00a1": 1, "2015": 10, "estar\u00e3\u00a1n": 3, "obligados": 5, "promover": 4, "equipos": 3, "receptores": 1, "decodificadores": 1, "adopci\u00e3\u00b3n": 1, "garantizando": 2, "permisionarios": 2, "est\u00e3\u00a1n": 3, "devolver": 1, "cuanto": 1, "culmine": 1, "originalmente": 1, "concesionadas": 1, "eficiente": 6, "\u00e3\u00b3ptimo": 2, "banda": 5, "700": 3, "mhz": 4, "escalonamiento": 2, "comisionados": 22, "econ\u00e3\u00b3mica": 7, "esos": 1, "2017": 7, "2018": 16, "2019": 5, "2020": 5, "2021": 2, "2022": 3, "se\u00e3\u00b1alar\u00e3\u00a1": 1, "observarse": 3, "comit\u00e3\u00a9": 9, "enviar": 1, "aspirantes": 2, "decreto;": 2, "recibidas": 1, "remitir": 4, "propuestas": 3, "siguientes;": 1, "reunido": 1, "propuesta": 5, "respecto": 5, "vacante": 2, "apruebe": 4, "ocasiones": 1, "comisionado": 13, "s\u00e3\u0089ptimo": 3, "integran": 1, "desconcentrados": 4, "referidos": 1, "crean": 1, "recaigan": 1, "impugnadas": 3, "juicio": 3, "indirecto": 4, "realizado": 2, "ejercer\u00e3\u00a1n": 3, "presten": 5, "radiodifundida": 5, "permitir": 2, "restringida": 4, "retransmisi\u00e3\u00b3n": 5, "se\u00e3\u00b1al": 4, "gratuita": 2, "discriminatoria": 3, "zona": 3, "\u00e3\u00adntegra": 2, "simult\u00e3\u00a1nea": 2, "radiodifunde": 2, "retransmitir": 4, "incluirla": 1, "costo": 3, "adicional": 4, "contratados": 2, "suscriptores": 3, "usuarios": 5, "obligatoriamente": 1, "se\u00e3\u00b1ales": 2, "radiodifundidas": 2, "cincuenta": 3, "territorio": 2, "declarados": 1, "sustancial": 3, "cualquiera": 4, "mercados": 3, "tendr\u00e3\u00a1n": 5, "regla": 2, "gratuidad": 2, "contenidos": 9, "gratuita;": 1, "ning\u00e3\u00ban": 6, "reflejar\u00e3\u00a1": 1, "acordar": 2, "precios": 7, "radiodifundidos": 3, "diferendo": 2, "tarifa": 2, "sancionar\u00e3\u00a1": 1, "revocaci\u00e3\u00b3n": 2, "beneficien": 1, "tambi\u00e3\u00a9n": 3, "revocar\u00e3\u00a1": 1, "gratuitamente": 1, "perder\u00e3\u00a1n": 1, "simult\u00e3\u00a1neamente": 1, "declaraci\u00e3\u00b3n": 1, "realizada": 4, "orientada": 1, "costos": 2, "cabal": 2, "licitaci\u00e3\u00b3n": 3, "adjudicaci\u00e3\u00b3n": 4, "convocatorias": 2, "licitar": 1, "agrupadas": 1, "cadenas": 2, "funcionamiento": 13, "barreras": 1, "caracter\u00e3\u00adsticas": 6, "existentes": 2, "abierta": 1, "participar": 4, "licitaciones": 3, "grupos": 2, "v\u00e3\u00adnculos": 1, "organizativo": 1, "acumulen": 1, "existencia": 1, "impondr\u00e3\u00a1": 2, "evitar": 1, "ello": 8, "emitir\u00e3\u00a1n": 1, "relacionadas": 2, "acuerdos": 8, "exclusiva": 3, "limitaciones": 1, "terminales": 1, "regulaci\u00e3\u00b3n": 11, "asim\u00e3\u00a9trica": 1, "infraestructuras": 1, "red": 17, "desagregaci\u00e3\u00b3n": 3, "esenciales": 1, "separaci\u00e3\u00b3n": 3, "contable": 2, "funcional": 2, "considerar\u00e3\u00a1": 4, "raz\u00e3\u00b3n": 7, "cuente": 3, "medido": 1, "porcentaje": 4, "n\u00e3\u00bamero": 5, "audiencia": 1, "tr\u00e3\u00a1fico": 1, "utilizada": 1, "disponga": 8, "impuestas": 1, "extinguir\u00e3\u00a1n": 1, "f\u00e3\u00adsicos": 1, "t\u00e3\u00a9cnicos": 3, "l\u00e3\u00b3gicos": 1, "conexi\u00e3\u00b3n": 1, "punto": 4, "terminal": 1, "pertenecientes": 1, "relevante": 1, "usuario": 1, "considerar": 3, "insumo": 1, "esencial": 1, "citadas": 4, "calendario": 2, "implantaci\u00e3\u00b3n": 2, "procurar": 2, "universal": 6, "aumento": 1, "penetraci\u00e3\u00b3n": 1, "verificar": 1, "recabar\u00e3\u00a1": 1, "constituir": 1, "relaci\u00e3\u00b3n": 3, "pronunciar\u00e3\u00a1n": 1, "falta": 1, "disposici\u00e3\u00b3n": 8, "expresa": 2, "administrativo;": 1, "\u00e3\u009anicamente": 2, "generales": 16, "aplicadas": 1, "intraprocesales": 1, "reclamarse": 1, "promovido": 1, "contra": 4, "admitir\u00e3\u00a1n": 1, "recurso": 1, "administrativo": 4, "alguno": 6, "solamente": 1, "incumplimiento": 4, "contempladas": 1, "d\u00e3\u0089cimo": 26, "independencia": 3, "editorial;": 1, "financiera;": 1, "ciudadana;": 1, "reglas": 14, "claras": 1, "rendici\u00e3\u00b3n": 2, "cuentas;": 1, "defensa": 3, "contenidos;": 1, "opciones": 1, "financiamiento;": 1, "tecnolog\u00e3\u00adas": 4, "expresi\u00e3\u00b3n": 1, "diversidades": 1, "ideol\u00e3\u00b3gicas": 1, "\u00e3\u00a9tnicas": 1, "culturales": 1, "equilibrada": 1, "dotar\u00e3\u00a1": 1, "vigilar": 1, "tiempos": 3, "m\u00e3\u00a1ximos": 1, "transmisi\u00e3\u00b3n": 7, "mensajes": 1, "comerciales": 3, "programaci\u00e3\u00b3n": 2, "dirigida": 1, "infantil": 2, "respete": 2, "espec\u00e3\u00adficos": 4, "regulen": 1, "pautada": 1, "destinada": 1, "supervisar": 4, "desacuerdo": 1, "colegiados": 2, "juzgados": 2, "especializados": 2, "emitir\u00e3\u00a1": 6, "prever\u00e3\u00a1n": 2, "rotaci\u00e3\u00b3n": 1, "conocer\u00e3\u00a1n": 2, "mismos": 2, "objetividad": 1, "imparcialidad": 1, "aprobar\u00e3\u00a1": 3, "dotar": 1, "reguladores": 3, "previsiones": 5, "presupuestarias": 2, "buen": 1, "inclusi\u00e3\u00b3n": 3, "objetivos": 6, "metas": 3, "accesibilidad": 2, "conectividad": 1, "habilidades": 1, "digitales": 2, "abiertos": 1, "privada": 4, "aplicaciones": 2, "telesalud": 1, "telemedicina": 1, "expediente": 1, "cl\u00e3\u00adnico": 1, "electr\u00e3\u00b3nico": 3, "aspectos": 1, "otras": 9, "70": 1, "hogares": 1, "micros": 1, "peque\u00e3\u00b1as": 1, "medianas": 1, "accesos": 1, "velocidad": 1, "real": 1, "descarga": 1, "promedio": 1, "registrado": 1, "pa\u00e3\u00adses": 1, "organizaci\u00e3\u00b3n": 10, "cooperaci\u00e3\u00b3n": 1, "caracter\u00e3\u00adstica": 1, "ofrecida": 1, "competitivos": 2, "internacionalmente": 1, "contribuir": 2, "elaborar\u00e3\u00a1": 2, "pol\u00e3\u00adticas": 2, "tendientes": 1, "internet": 1, "ancha": 4, "edificios": 2, "instalaciones": 4, "har\u00e3\u00a1n": 2, "electricidad": 11, "ceder\u00e3\u00a1": 1, "totalmente": 1, "operar": 3, "explotar": 1, "transferir\u00e3\u00a1": 1, "fibra": 2, "\u00e3\u00b3ptica": 2, "poster\u00e3\u00ada": 2, "efectivo": 4, "compartido": 2, "adecuado": 4, "planear": 1, "dise\u00e3\u00b1ar": 1, "ejecutar": 1, "crecimiento": 5, "robusta": 1, "troncal": 3, "tel\u00e3\u00a9grafos": 1, "garantizar\u00e3\u00a1": 3, "instalaci\u00e3\u00b3n": 11, "compartida": 4, "impulse": 1, "2014": 14, "2018;": 2, "contemplar\u00e3\u00a1": 1, "liberado": 1, "(banda": 1, "mhz)": 1, "activo": 2, "utilizarse": 1, "compartida;": 3, "contemplar": 2, "identificando": 1, "necesidades": 1, "diputados;": 2, "asegurar\u00e3\u00a1": 2, "prestador": 1, "tenga": 3, "influencia": 1, "red;": 1, "activos": 2, "requeridos": 1, "servicios;": 2, "operar\u00e3\u00a1": 3, "compartici\u00e3\u00b3n": 2, "toda": 6, "venta": 2, "desagregada": 2, "prestar\u00e3\u00a1": 1, "exclusivamente": 3, "comercializadoras": 1, "operadoras": 1, "discriminaci\u00e3\u00b3n": 1, "obligar\u00e3\u00a1n": 1, "comercializadores": 1, "reciban": 1, "promover\u00e3\u00a1": 1, "tarifaria": 1, "fomente": 1, "asegure": 1, "reinversi\u00e3\u00b3n": 1, "utilidades": 1, "incluir\u00e3\u00a1": 4, "program\u00e3\u00a1ticos": 2, "plan": 6, "sectoriales": 1, "institucionales": 2, "acciones:": 1, "mixta": 1, "poblaci\u00e3\u00b3n;": 1, "sitios": 3, "identifique": 2, "conectar": 1, "alcanzar": 1, "universal;": 1, "pormenorizado": 1, "ductos": 4, "puestos": 1, "agilizar": 1, "despliegue": 1, "contraprestaci\u00e3\u00b3n": 4, "pagar": 1, "discriminatorio": 3, "promuevan": 1, "ofrezca": 1, "propia": 4, "infraestructura;": 1, "trabajo": 10, "enunciativa": 1, "limitativa": 1, "bandas": 1, "ghz": 1, "continuo": 1, "reorganizar": 1, "estaciones": 1, "fijados": 1, "dedicados": 1, "comprende": 2, "suprime": 1, "quedar\u00e3\u00a1": 1, "contravenga": 2, "procedimental": 4, "alternativos": 5, "soluci\u00e3\u00b3n": 5, "iniciarse": 2, "anaya": 6, "cortes": 1, "ra\u00e3\u00bal": 8, "cervantes": 7, "gomez": 1, "energ\u00e3\u00ada": 28, "25;": 1, "dedicadas": 2, "descentralizados": 4, "denominados": 2, "petr\u00e3\u00b3leos": 15, "conviertan": 3, "productivas": 13, "lleva": 1, "subsidiarios": 5, "quedan": 1, "facultados": 1, "recibir": 3, "asignaciones": 19, "suscribir": 1, "efectivas": 1, "contrataci\u00e3\u00b3n": 8, "otras:": 1, "utilidad": 3, "licencia": 2, "llevar": 11, "exploraci\u00e3\u00b3n": 20, "extracci\u00e3\u00b3n": 17, "petr\u00e3\u00b3leo": 22, "hidrocarburos": 37, "s\u00e3\u00b3lidos": 8, "l\u00e3\u00adquidos": 8, "gaseosos": 7, "definir\u00e3\u00a1": 2, "contractual": 1, "convenga": 1, "maximizar": 3, "pagar\u00e3\u00a1": 1, "regularse": 1, "i)": 6, "ii)": 1, "iii)": 1, "obtenida": 1, "iv)": 1, "onerosa": 1, "extra\u00e3\u00addos": 2, "subsuelo": 4, "v)": 1, "combinaci\u00e3\u00b3n": 1, "escoger\u00e3\u00a1": 1, "beneficio": 4, "regular\u00e3\u00a1": 1, "favor": 1, "productos": 2, "transfieran": 3, "suscriban": 2, "contrato": 4, "reportar": 2, "contables": 2, "esperados": 1, "afirme": 1, "ramo": 24, "asistencia": 6, "encargada": 3, "adjudicar": 1, "\u00e3\u00a1reas": 3, "acreditar": 1, "financieras": 1, "explorar": 1, "extraer": 1, "competitiva": 2, "presentar": 2, "estableciendo": 1, "superficie": 2, "profundidad": 3, "procedentes": 1, "tomando": 5, "aspectos:": 1, "hidrocarburos:": 3, "descubrimientos": 1, "inversiones": 6, "claramente": 1, "\u00e3\u00a1rea": 4, "asignada": 1, "trabajos": 4, "prorrogables": 1, "campo": 2, "cumplirse": 1, "cuesti\u00e3\u00b3n": 2, "revertirse": 1, "incluya": 2, "descripciones": 1, "justificando": 1, "determinaci\u00e3\u00b3n": 1, "coexistencia": 2, "determinada": 1, "espec\u00e3\u00adfica": 1, "extractivas": 1, "realizadas": 1, "separado": 1, "ubiquen": 1, "diferente": 1, "prospectivos": 1, "hace": 9, "menci\u00e3\u00b3n": 1, "llegaran": 1, "afectar": 1, "\u00e3\u00a9stas": 4, "reconocidas": 1, "justo": 1, "valor": 17, "transferidas": 1, "migraci\u00e3\u00b3n": 2, "adjudiquen": 1, "elija": 1, "contratar": 1, "contratista": 1, "llevar\u00e3\u00a1": 5, "contractuales": 1, "sujeta": 2, "control": 15, "suscritos": 3, "nacionales": 4, "porcentajes": 1, "m\u00e3\u00adnimos": 3, "proveedur\u00e3\u00ada": 1, "fomentar": 2, "industria": 5, "ajustarse": 2, "tratados": 1, "internacionales": 1, "derivado": 1, "estrat\u00e3\u00a9gico": 1, "el\u00e3\u00a9ctrica": 5, "consideran": 2, "preferencia": 2, "otra": 1, "implique": 1, "terrenos": 1, "afectos": 1, "aqu\u00e3\u00a9llas": 3, "cubrir": 10, "ocupaci\u00e3\u00b3n": 1, "afectaci\u00e3\u00b3n": 1, "superficial": 1, "mineras": 1, "posterioridad": 1, "conferir\u00e3\u00a1n": 1, "propias": 2, "fuere": 2, "t\u00e3\u00a9cnicamente": 1, "facilitar": 2, "realicen": 7, "suscriba": 1, "otorgados": 3, "garanticen": 1, "instauren": 1, "debidamente": 1, "difundidas": 1, "p\u00e3\u00bablicamente": 1, "consultables": 1, "regular\u00e3\u00a1:": 1, "cl\u00e3\u00a1usulas": 1, "posibiliten": 1, "interesado": 1, "consultar;": 1, "auditor\u00e3\u00adas": 1, "externas": 1, "recuperaci\u00e3\u00b3n": 1, "incurridos": 1, "contabilidad": 3, "involucrada": 1, "divulgaci\u00e3\u00b3n": 2, "pagos": 5, "federal:": 1, "energ\u00e3\u00ada:": 2, "conducir": 2, "coordinar": 1, "energ\u00e3\u00a9tica": 2, "selecci\u00e3\u00b3n": 2, "hidrocarburos;": 2, "t\u00e3\u00a9cnico": 6, "licitaci\u00e3\u00b3n;": 1, "otorgamiento": 4, "tratamiento": 3, "refinaci\u00e3\u00b3n": 1, "procesamiento": 1, "gas": 8, "estricta": 1, "requieren": 1, "abierto": 2, "el\u00e3\u00a9ctrico": 3, "vigilar\u00e3\u00a1": 1, "asesor\u00e3\u00ada": 1, "energ\u00e3\u00ada;": 1, "recopilaci\u00e3\u00b3n": 1, "geol\u00e3\u00b3gica": 1, "operativa;": 1, "reconocimiento": 3, "superficial;": 1, "ganadores": 1, "suscripci\u00e3\u00b3n": 1, "gaseosos;": 1, "contratos;": 1, "supervisi\u00e3\u00b3n": 1, "maximicen": 1, "productividad": 1, "reguladora": 4, "almacenamiento": 5, "transporte": 5, "petrol\u00e3\u00adferos": 1, "petroqu\u00e3\u00admicos;": 1, "derivados": 5, "ventas": 1, "mano": 1, "generaci\u00e3\u00b3n": 3, "porteo": 1, "establecimiento": 2, "econ\u00e3\u00b3micas": 1, "contribuyan": 2, "omisiones": 2, "den": 1, "imposici\u00e3\u00b3n": 1, "sanciones": 6, "dependencia": 5, "imponerlas": 1, "ejecutarlas": 1, "lleven": 1, "mantenimiento": 2, "coordinados": 1, "personalidad": 1, "jur\u00e3\u00addica": 3, "gesti\u00e3\u00b3n;": 1, "disponer": 2, "aprovechamientos": 2, "centro": 12, "financiar": 3, "menos:": 3, "finalizar": 2, "existiera": 2, "saldo": 14, "remanente": 2, "propios": 2, "excedentes": 2, "instruir\u00e3\u00a1": 3, "fideicomiso": 9, "instituci\u00e3\u00b3n": 5, "banca": 3, "fiduciario": 5, "instruir\u00e3\u00a1n": 1, "fideicomisos": 4, "respetando": 4, "referencia": 13, "estando": 2, "sujetos": 4, "entes": 3, "fiscalizadores": 3, "prioridad": 1, "contendr\u00e3\u00a1": 2, "estudios": 1, "s\u00e3\u00adsmicos": 1, "n\u00e3\u00bacleos": 1, "roca": 1, "obtenidos": 2, "acumular": 2, "equivalente": 12, "veces": 2, "anual": 5, "aprobado": 8, "transferidos": 7, "tesorer\u00e3\u00ada": 6, "publicar": 4, "sitio": 2, "trimestral": 4, "depositados": 2, "destino": 5, "cap\u00e3\u00adtulos": 2, "suministros": 2, "removidos": 4, "causas": 1, "efecto;": 1, "nuevamente": 1, "sujet\u00e3\u00a1ndose": 1, "comparecencia": 1, "designar\u00e3\u00a1": 3, "terceras": 11, "improrrogable": 1, "resolviere": 1, "ocupar\u00e3\u00a1": 2, "designe": 3, "rechace": 1, "totalidad": 3, "fuera": 1, "rechazada": 1, "nombrar\u00e3\u00a1n": 1, "estabilizaci\u00e3\u00b3n": 14, "banco": 2, "fungir\u00e3\u00a1": 2, "impuestos": 1, "administrar\u00e3\u00a1n": 1, "distribuir\u00e3\u00a1n": 1, "prelaci\u00e3\u00b3n": 1, "transferencias": 4, "petroleros": 7, "alcanzado": 2, "l\u00e3\u00admite": 3, "asignados": 2, "destinar\u00e3\u00a1n": 1, "ahorro": 13, "sustentabilidad": 1, "petrolera": 2, "transferir": 3, "destinan": 1, "mantengan": 1, "producto": 10, "interno": 7, "bruto": 6, "observada": 1, "rubros": 3, "extraordinario": 1, "exportaci\u00e3\u00b3n": 1, "crudo": 1, "cient\u00e3\u00adfica": 1, "tecnol\u00e3\u00b3gica": 1, "considerar\u00e3\u00a1n": 2, "incluidos": 2, "acorde": 2, "numerales": 2, "igual": 5, "previo": 2, "acumulado": 2, "incremento": 7, "observado": 4, "pensi\u00e3\u00b3n": 1, "ley;": 2, "proyectos": 7, "ciencia": 1, "tecnolog\u00e3\u00ada": 1, "innovaci\u00e3\u00b3n": 1, "energ\u00e3\u00adas": 2, "renovables;": 1, "fondear": 1, "veh\u00e3\u00adculo": 1, "especializado": 1, "sectorizado": 1, "plazo;": 1, "becas": 2, "capital": 2, "humano": 1, "universidades": 1, "posgrados;": 1, "mejora": 3, "conectividad;": 1, "emplearse": 1, "gasto": 4, "corriente": 2, "destinado": 2, "reduzca": 1, "debajo": 2, "posibles": 1, "destinos": 2, "mencionados": 1, "rendimientos": 1, "reales": 1, "anuales": 1, "asociados": 1, "reducci\u00e3\u00b3n": 2, "significativa": 1, "asociada": 1, "ca\u00e3\u00adda": 2, "disminuci\u00e3\u00b3n": 3, "pronunciada": 1, "precio": 1, "agotado": 1, "votaci\u00e3\u00b3n": 8, "a\u00e3\u00ban": 1, "redujera": 1, "seguimiento": 2, "constituir\u00e3\u00a1": 2, "operaciones": 5, "independientes": 13, "secretar\u00e3\u00adas": 4, "gobernador": 1, "atribuciones:": 1, "instruir": 1, "fiduciaria": 1, "realice": 5, "recomendar": 1, "montos": 2, "estime": 1, "convenientes": 1, "mencionada": 1, "asignar": 2, "pronuncie": 1, "acerca": 1, "recomendaci\u00e3\u00b3n": 1, "aprobada": 4, "asignar\u00e3\u00a1n": 1, "rubro": 2, "proyecto": 8, "reasignar": 1, "se\u00e3\u00b1alan": 1, "continuaci\u00e3\u00b3n": 4, "decretos:": 1, "divisiones": 1, "adquiera": 1, "administre": 2, "ducto": 2, "inmediata": 2, "apoyo": 3, "operando": 2, "brinde": 1, "continuidad": 4, "eficiencia": 5, "operativo": 1, "nacional;": 2, "mayorista;": 1, "indebidamente": 1, "requiera": 3, "trescientos": 2, "procurar\u00e3\u00a1": 1, "cuidado": 1, "intervengan": 1, "incorporaci\u00e3\u00b3n": 4, "mejores": 5, "temas": 2, "gases": 1, "compuestos": 1, "invernadero": 1, "baja": 1, "residuos": 2, "emisiones": 3, "huella": 1, "carbono": 1, "participantes": 1, "limpias": 1, "contaminantes": 1, "conducto": 3, "sustentable": 1, "estrategia": 1, "combustibles": 1, "limpios": 1, "geot\u00e3\u00a9rmicos": 1, "generar": 2, "destinarla": 1, "usos": 1, "agencia": 8, "industrial": 2, "operativa": 2, "desmantelamiento": 1, "abandono": 1, "vig\u00e3\u00a9simo": 5, "que:": 1, "incrementar": 1, "sujetas": 1, "balance": 1, "financiero": 2, "techo": 2, "distinto": 1, "estructura": 4, "corporativa": 1, "acordes": 1, "internacional": 1, "obtenci\u00e3\u00b3n": 3, "arreglo": 1, "institucional": 1, "presidir\u00e3\u00a1": 1, "conduzcan": 1, "reducir": 1, "fuentes": 1, "adquisiciones": 1, "arrendamientos": 1, "deuda": 2, "eficaz": 1, "competir": 1, "eficacia": 2, "actividad": 1, "profesionales": 1, "convierta": 1, "empresa": 2, "productiva": 2, "citados": 1, "considerados": 3, "suficientes": 1, "investigar": 1, "identificar": 1, "asignatarios": 1, "contratistas": 1, "moral": 1, "participen": 1, "energ\u00e3\u00a9tico": 1, "contrarios": 1, "influir": 1, "toma": 1, "decisi\u00e3\u00b3n": 1, "servidor": 1, "directo": 1, "raymundo": 1, "king": 1, "xxix-r": 5, "solicitar\u00e3\u00a1": 1, "opini\u00e3\u00b3n": 2, "adecuar\u00e3\u00a1n": 2, "carre\u00e3\u00b1o": 1, "mijares": 1, "elena": 5, "barrera": 5, "tapia": 5, "xxix-s": 1, "xxix-t": 1, "subsecuente;": 1, "xix": 2, "h)": 5, "110;": 2, "111;": 2, "\u00e3\u00b1)": 1, "\u00e2\u0080\u00a6\u00e2\u0080\u00a6": 1, "gubernamental": 2, "impugnaci\u00e3\u00b3n": 1, "conforman": 1, "aut\u00e3\u00b3nomo": 5, "petici\u00e3\u00b3n": 3, "formal": 1, "reste": 1, "extingue": 1, "contrario": 4, "entender\u00e3\u00a1": 6, "negativa": 2, "integra": 1, "garante": 9, "supuesto": 3, "obtengan": 3, "transitoria": 1, "formar\u00e3\u00a1n": 1, "terminaci\u00e3\u00b3n": 2, "originariamente": 2, "algunas": 1, "algunos": 1, "confiri\u00e3\u00b3": 1, "extingue;": 1, "designar\u00e3\u00a1n": 1, "hip\u00e3\u00b3tesis": 2, "formen": 1, "esa": 4, "fenecido": 1, "comisionada": 1, "concluye": 1, "habr\u00e3\u00ada": 3, "ambas": 2, "comisionadas": 1, "habr\u00e3\u00adan": 1, "ninguno": 1, "solicite": 2, "reciba": 1, "especificar\u00e3\u00a1": 2, "nombrar\u00e3\u00a1": 7, "cuyos": 4, "2023": 2, "sustituya": 3, "deja": 3, "2026": 1, "sustituyan": 2, "dejan": 1, "armonizar": 2, "normatividad": 1, "posterior": 3, "responsable": 2, "atender": 3, "sustanciar\u00e3\u00a1n": 1, "2014-": 6, "ver\u00e3\u00b3nica": 1, "beatriz": 1, "ju\u00e3\u00a1rez": 1, "pi\u00e3\u00b1a": 1, "catorce-": 6, "pol\u00e3\u00adtica-electoral": 1, "26;": 2, "apartados": 1, "41;": 3, "54;": 2, "55;": 2, "59;": 1, "65;": 2, "82;": 1, "93;": 1, "95;": 2, "xv": 3, "107;": 3, "encabezado": 1, "j)": 3, "k)": 3, "119;": 1, "xxix-u": 2, "90;": 2, "n)": 3, "locales:": 1, "intervenci\u00e3\u00b3n": 1, "locales;": 2, "militantes": 1, "garant\u00e3\u00ada": 4, "imparciales": 1, "intrapartidaria;": 1, "directivos;": 1, "postulaci\u00e3\u00b3n": 1, "conducci\u00e3\u00b3n": 2, "democr\u00e3\u00a1tica;": 1, "recursos;": 1, "documentos": 2, "b\u00e3\u00a1sicos;": 1, "obligaciones;": 1, "figura": 2, "coaliciones": 7, "uniforme": 1, "etapa": 2, "precampa\u00e3\u00b1as;": 1, "diferenciar\u00e3\u00a1": 1, "totales": 1, "parciales": 1, "flexibles": 1, "coalici\u00e3\u00b3n": 4, "postular": 3, "parcial": 1, "candidaturas": 6, "flexible": 1, "electoral;": 3, "aparecer\u00e3\u00a1n": 1, "emblemas": 1, "boletas": 1, "escrutinio": 2, "c\u00e3\u00b3mputo": 2, "votos;": 1, "participe": 1, "coaligarse": 1, "origen": 4, "contener:": 1, "expedita": 1, "oportuna": 1, "homog\u00e3\u00a9neos": 1, "electr\u00e3\u00b3nicos;": 1, "notificar": 1, "celebren": 1, "campa\u00e3\u00b1as": 2, "notificaciones": 1, "entrega": 2, "trate;": 1, "comprobar": 1, "avisos": 2, "previos": 2, "anterior;": 3, "movimientos": 1, "requerimientos": 1, "validaci\u00e3\u00b3n": 1, "contrataciones": 1, "optar": 2, "relativos": 3, "general;": 1, "exterior": 2, "imponerse": 1, "electorales:": 1, "celebraci\u00e3\u00b3n": 1, "domingo": 3, "verifiquen": 2, "julio;": 1, "inteligencia": 1, "financiera": 2, "consideren": 1, "relevantes": 1, "inusuales": 1, "aplicables;": 1, "transparentar": 1, "metodolog\u00e3\u00ada": 1, "encuestas": 1, "difundan": 1, "preferencias": 1, "difusi\u00e3\u00b3n;": 1, "habr\u00e3\u00a1n": 1, "debates": 3, "obligatorio": 2, "organizados": 1, "electorales;": 1, "organizar": 1, "popular": 3, "cancelaci\u00e3\u00b3n": 1, "debate": 2, "prueba": 2, "ilegal": 1, "propaganda": 3, "encubierta;": 1, "televisi\u00e3\u00b3n;": 1, "denuncias": 1, "fr\u00e3\u00advolas": 1, "fr\u00e3\u00advola": 1, "aquella": 2, "promueva": 1, "hechos": 4, "soportados": 1, "actualizar": 4, "espec\u00e3\u00adfico": 1, "sustente": 1, "queja": 1, "denuncia;": 1, "debiendo": 2, "promocionales": 1, "utilitarios": 1, "elaborados": 1, "material": 1, "textil;": 1, "paridad": 1, "g\u00e3\u00a9neros": 1, "legisladores": 3, "instancias": 1, "etapas": 2, "violaciones": 1, "formas": 2, "lxii": 1, "reglamente": 1, "sujetarse": 3, "aut\u00e3\u00b3nomos": 2, "ente": 1, "cumpla": 1, "econom\u00e3\u00ada": 1, "honradez": 1, "topes": 1, "derogaciones": 5, "f);": 1, "conserven": 1, "integrarse": 2, "otorgan": 1, "separados": 1, "p\u00e3\u00a1rrafo:": 1, "quede": 2, "menoscabo": 1, "casillas": 2, "mesa": 4, "directiva": 4, "delegadas": 1, "reasumir": 1, "delegaci\u00e3\u00b3n": 1, "reasunci\u00e3\u00b3n": 1, "designaciones": 1, "verifique": 2, "antelaci\u00e3\u00b3n": 4, "d\u00e3\u0089cimo-": 2, "jurisdiccionales": 2, "elegibles": 1, "59": 1, "tercero;": 3, "xi;": 2, "reelecci\u00e3\u00b3n": 2, "protestado": 2, "regidores": 1, "s\u00e3\u00adndicos": 1, "83": 1, "2024": 2, "segundo;": 11, "supresi\u00e3\u00b3n": 1, "procurador": 4, "xii;": 2, "v;": 3, "ix;": 3, "a;": 1, "rep\u00e3\u00bablica;": 1, "haga": 3, "fiscal\u00e3\u00ada": 4, "estuviere": 1, "reunida": 1, "convocar\u00e3\u00a1": 1, "inmediatamente": 1, "sesi\u00e3\u00b3n": 4, "extraordinaria": 2, "27-08-2018": 2, "expedirse": 2, "referidas": 5, "forma:": 1, "i-": 1, "procuradur\u00e3\u00ada": 4, "ejercitado": 1, "remitirse": 1, "suspender\u00e3\u00a1n": 1, "decretada": 1, "oficio": 1, "desahoguen": 1, "ii-": 1, "destine": 1, "atenci\u00e3\u00b3n": 10, "desahogo": 1, "queden": 1, "especializada": 2, "objetar": 1, "corrupci\u00e3\u00b3n": 3, "fiscal\u00e3\u00adas": 1, "objetada": 1, "restituido": 1, "vig\u00e3\u0089simo-": 1, "regir\u00e3\u00a1": 3, "vig\u00e3\u0089simo": 1, "v\u00e3\u00a1lidamente": 1, "surtir\u00e3\u00a1n": 1, "fuente": 2, "haciendas": 1, "c\u00e3\u00b3digos": 1, "exenci\u00e3\u00b3n": 1, "copia": 1, "certificada": 1, "acta": 2, "formato": 1, "implementarse": 1, "adoptarse": 1, "representaciones": 1, "remitir\u00e3\u00a1": 1, "recabada": 1, "registrales": 1, "certificados": 1, "defunci\u00e3\u00b3n": 1, "pablo": 4, "alem\u00e3\u00a1n": 1, "2015-": 6, "barbosa": 5, "huerta": 7, "augusto": 1, "chan": 1, "lugo": 1, "quince-": 4, "disciplina": 4, "cuarto;": 4, "117": 4, "subsecuentes;": 1, "xxix-w;": 1, "hacendaria": 2, "xxix-w": 1, "publicarse": 1, "adquiridas": 1, "transitoriedad": 1, "restricciones": 1, "corto": 1, "enviar\u00e3\u00a1n": 1, "empr\u00e3\u00a9stitos": 3, "empr\u00e3\u00a9stito": 1, "obligaciones:": 1, "deudor": 1, "acreedor": 1, "tasa": 3, "fortalecimiento": 3, "implementa": 2, "pondr\u00e3\u00a1": 1, "reporte": 1, "igualmente": 1, "informar": 1, "cierre": 1, "(marzo": 1, "diciembre)": 1, "registrados": 2, "especificando": 1, "fue": 1, "utilizado": 1, "refinanciar": 1, "reestructurar": 1, "cr\u00e3\u00a9ditos": 6, "puntual": 1, "endeudamiento": 1, "auditor\u00e3\u00ada": 2, "publicar\u00e3\u00a1n": 1, "referente": 1, "responsables": 1, "manejo": 1, "responder\u00e3\u00a1n": 1, "da\u00e3\u00b1os": 1, "perjuicios": 1, "ocasionen": 1, "contratarse": 1, "sandoval": 3, "combate": 1, "d\u00e3\u00a9cimo;": 1, "xxiv": 3, "xxix-h;": 1, "\u00e2\u0080\u009dde": 1, "vinculados": 1, "faltas": 2, "estado\u00e2\u0080\u009d;": 1, "109;": 1, "113;": 1, "114": 2, "m)": 2, "quinta;": 1, "xxix-v;": 1, "xxix-v": 1, "asuma": 1, "derivan": 1, "observando": 1, "administrativa:": 1, "sujeci\u00e3\u00b3n": 2, "techos": 1, "globales": 1, "federal;": 1, "p\u00e3\u00bablica;": 3, "autorizar\u00e3\u00a1": 1, "requerir": 1, "rebase": 1, "global": 1, "ajustes": 2, "informes": 2, "109": 2, "quinta": 1, "anticorrupci\u00e3\u00b3n": 1, "conformarse": 1, "administrativa": 9, "contenciosos": 1, "funcionando": 1, "prestando": 1, "conservando": 1, "corresponden": 1, "roc\u00e3\u00ado": 1, "gallegos": 1, "previendo": 1, "transitorias": 1, "diferenciar": 1, "abroga": 1, "menores": 1, "infractores": 1, "fuero": 2, "sancionadoras": 2, "prop\u00e3\u00b3sitos": 1, "b\u00e3\u00basqueda": 1, "desaparici\u00e3\u00b3n": 1, "forzada": 1, "privaci\u00e3\u00b3n": 1, "contrarias": 1, "tortura": 1, "tratos": 1, "crueles": 1, "inhumanos": 1, "degradantes": 1, "\u00e3\u00baltimas": 1, "desindexaci\u00e3\u00b3n": 1, "salario": 10, "m\u00e3\u00adnimo": 10, "unidad": 18, "actualice": 1, "mensual": 4, "multiplicar": 4, "304": 2, "menciones": 1, "\u00e3\u00adndice": 3, "cuant\u00e3\u00ada": 1, "supuestos": 2, "emane": 2, "administraciones": 1, "eliminar": 1, "sustituirlas": 1, "promulga": 1, "utilizar\u00e3\u00a1": 2, "m\u00e3\u00a9todo": 1, "actualizaci\u00e3\u00b3n:": 1, "multiplicando": 1, "suma": 1, "variaci\u00e3\u00b3n": 1, "interanual": 1, "\u00e3\u008dndice": 1, "consumidor": 1, "periodicidad": 1, "anualidad": 1, "ajuste": 2, "actualizar\u00e3\u00a1": 1, "actualicen": 2, "vivienda": 6, "actualiz\u00e3\u00a1ndose": 1, "estipulados": 1, "evento": 2, "incremente": 2, "encima": 2, "inflaci\u00e3\u00b3n": 3, "moneda": 2, "supere": 2, "porcentual": 2, "720": 1, "otorgando": 1, "referencien": 1, "mecanismo": 2, "implementar": 2, "naturaleza": 1, "utilicen": 1, "modificar\u00e3\u00a1n": 1, "acuerden": 1, "contratantes": 1, "utilizar": 1, "coberturas": 1, "respaldados": 1, "bancario": 1, "hipotecaria": 1, "snc": 1, "mensualidades": 1, "acreditados": 1, "gestiones": 1, "abrogan": 1, "excepto": 2, "denominada": 1, "udi": 1, "2016-": 4, "zambrano": 2, "grijalva": 2, "teresa": 1, "liz\u00e3\u00a1rraga": 1, "figueroa": 1, "diecis\u00e3\u00a9is-": 4, "s\u00e3\u00a9ptimo;": 3, "a);": 1, "iv;": 3, "36": 2, "40;": 1, "43;": 1, "44;": 1, "53": 1, "62;": 1, "xxviii": 1, "xxix-c": 1, "xxix-g": 1, "xxix-i": 1, "xxix-k": 1, "xxix-": 1, "n": 1, "xxix-t;": 1, "xiv;": 1, "101": 1, "h);": 1, "106;": 1, "120;": 1, "121": 1, "xxxi": 4, "124;": 1, "125;": 1, "130": 1, "131": 1, "133;": 1, "135": 1, "faculta": 3, "inherentes": 2, "ejerzan": 2, "alcald\u00e3\u00adas": 8, "divisi\u00e3\u00b3n": 1, "concejos": 1, "integrar\u00e3\u00a1n": 2, "alcalde": 2, "concejales": 1, "proporci\u00e3\u00b3n": 1, "pol\u00e3\u00adtico-": 1, "postulados": 2, "ajustar\u00e3\u00a1n": 1, "normar": 1, "hubiere": 2, "emanado": 1, "ejerce": 1, "atribuci\u00e3\u00b3n": 1, "regido": 1, "norm\u00e3\u00a1ndose": 1, "susciten": 1, "resolver\u00e3\u00a1n": 1, "conciliaci\u00e3\u00b3n": 7, "arbitraje": 4, "paraestatales": 1, "rija": 1, "incorporados": 2, "convenio": 1, "afiliaci\u00e3\u00b3n": 1, "constituyente": 24, "compondr\u00e3\u00a1": 1, "constituyentes": 10, "votada": 1, "t\u00e3\u00a9rminos:": 1, "integradas": 2, "propietarios": 2, "requerir\u00e3\u00a1": 1, "manifestaci\u00e3\u00b3n": 1, "voluntad": 1, "candidato": 2, "firma": 1, "cantidad": 1, "nominal": 1, "electores": 2, "nombres": 1, "ordenados": 1, "descendente": 1, "boleta": 1, "aparecer": 1, "recuadro": 1, "elector": 1, "asiente": 2, "identific\u00e3\u00a1ndolos": 1, "nombre": 2, "bastar\u00e3\u00a1": 1, "apellido": 1, "propietario": 1, "indubitable": 1, "c\u00e3\u00b3mputos": 1, "obtenido": 1, "diputaciones": 5, "asignar\u00e3\u00a1n:": 1, "dividir": 2, "v\u00e3\u00a1lida": 1, "emitida": 2, "restantes": 2, "deducidos": 1, "votos": 2, "tuviesen": 1, "quedaren": 1, "distribuir": 1, "tuvieren": 1, "electo": 2, "diputado": 3, "requisitos:": 1, "derechos;": 1, "cumplidos": 1, "elecci\u00e3\u00b3n;": 10, "originario": 1, "vecino": 1, "\u00e3\u00a9l": 1, "ella;": 1, "inscrito": 1, "credencial": 1, "votar;": 1, "ej\u00e3\u00a9rcito": 1, "mando": 3, "polic\u00e3\u00ada": 7, "separen": 8, "subsecretario": 1, "ministro": 2, "miembro": 2, "magistrado": 3, "distritales": 1, "institutos": 1, "pertenecer": 1, "definitivamente": 1, "legislador": 1, "delegacional": 1, "resultando": 1, "125": 1, "contencioso": 2, "alg\u00e3\u00ban": 2, "culto": 1, "religioso;": 1, "padrones": 1, "afiliados": 1, "participado": 1, "precandidatos": 1, "inmediatas": 1, "convocatoria": 2, "ajustar\u00e3\u00a1": 1, "circunscribirse": 2, "aplicar": 1, "estricto": 1, "legalidad": 2, "impugnaciones": 1, "determinan": 1, "catorce": 3, "62": 1, "honor\u00e3\u00adfica": 1, "percibir\u00e3\u00a1n": 1, "instalarse": 1, "constitutiva": 1, "actuar\u00e3\u00a1n": 1, "instaladora": 6, "constituida": 1, "vicepresidentes": 2, "secretarios": 2, "antig\u00e3\u00bcedad": 2, "mayores": 2, "antig\u00e3\u00bcedades": 2, "asistir\u00e3\u00a1n": 1, "sucesivas": 1, "discusi\u00e3\u00b3n": 2, "elaborar": 1, "discutido": 1, "votado": 1, "limitaci\u00e3\u00b3n": 1, "celebre": 1, "dict\u00e3\u00a1menes": 1, "vetada": 1, "remitida": 1, "publique": 1, "gaceta": 1, "desde": 1, "extraordinarias": 1, "2017-2018": 1, "cesar\u00e3\u00a1n": 1, "transcurrido": 1, "aqu\u00e3\u00a9lla": 2, "all\u00e3\u00a1": 1, "sesionar": 2, "direcci\u00e3\u00b3n": 1, "dictar": 1, "remitido": 1, "discutir": 1, "adicionar": 1, "votar": 1, "ordenar": 1, "gozar\u00e3\u00a1": 1, "plena": 1, "constituyente;": 1, "intervenir": 1, "interferir": 2, "sesionar\u00e3\u00a1": 2, "antigua": 1, "sede": 2, "xicot\u00e3\u00a9ncatl": 1, "circunstancias": 1, "ocupar": 2, "recinto": 2, "habilitaci\u00e3\u00b3n": 1, "recintos": 2, "ocupe": 2, "inviolables": 1, "auxilio": 1, "salvaguardar": 1, "inviolabilidad": 1, "determinaciones": 1, "discusiones": 1, "tema": 1, "circunstancia": 1, "relacionada": 1, "tampoco": 1, "pronunciamientos": 1, "tomar": 1, "ubicados": 1, "interpuestos": 3, "interposici\u00e3\u00b3n": 1, "sustanciaci\u00e3\u00b3n": 1, "conocidos": 1, "ocupado": 1, "titularidad": 1, "departamento": 1, "jefatura": 1, "interino": 1, "provisional": 1, "sustituto": 1, "despacho": 1, "acceder\u00e3\u00a1n": 1, "prevea": 2, "contemplar\u00e3\u00a1n": 1, "distribuirse": 1, "concejo": 1, "alcald\u00e3\u00ada": 1, "gerardo": 1, "hermosillo": 1, "arteaga": 1, "xxix-x": 2, "roberto": 2, "gil": 2, "zuarth": 2, "genoveva": 2, "villegas": 2, "regulatoria": 2, "c\u00e3\u00advica": 4, "itinerante": 4, "civiles": 3, "xxix-a": 3, "xxix-y": 3, "xxix-z": 3, "obligaci\u00e3\u00b3n": 3, "trabajar": 1, "formatos": 1, "accesibles": 1, "inscripci\u00e3\u00b3n;": 1, "estandarizaci\u00e3\u00b3n": 1, "actas": 2, "electr\u00e3\u00b3nica;": 1, "posibilidad": 1, "firmas": 1, "digitales;": 1, "consultas": 1, "remota;": 1, "alternos": 1, "situaci\u00e3\u00b3n": 1, "vulnerabilidad": 1, "marginaci\u00e3\u00b3n;": 1, "homologados": 2, "captura": 1, "datos;": 1, "simplificaci\u00e3\u00b3n": 1, "correcci\u00e3\u00b3n": 1, "rectificaci\u00e3\u00b3n": 1, "aclaraci\u00e3\u00b3n": 1, "expedidos": 1, "v\u00e3\u00a1lidos": 1, "cat\u00e3\u00a1logo": 2, "regulaciones": 1, "inscripci\u00e3\u00b3n": 1, "accesible": 1, "ciudadanos;": 1, "proveer\u00e3\u00a1n": 1, "2017-": 3, "escudero": 3, "edmundo": 2, "bola\u00e3\u00b1os": 2, "itzel": 1, "sarah\u00e3\u00ad": 1, "r\u00e3\u00ados": 1, "mora": 1, "dom\u00e3\u00adnguez": 1, "rex": 1, "quer\u00e3\u00a9taro": 1, "diecisiete-": 3, "xviii": 1, "xxvii": 1, "xxii": 1, "bis": 1, "elimina": 1, "instituyen": 1, "inician": 1, "juntas": 4, "previsi\u00e3\u00b3n": 2, "diferencias": 2, "colectivos": 3, "sindicales": 3, "conociendo": 1, "amparos": 1, "laudos": 1, "estuvieran": 1, "encargar\u00e3\u00a1": 2, "expedientes": 2, "documentaci\u00e3\u00b3n": 2, "resguardo": 2, "encargar\u00e3\u00a1n": 1, "patrones": 1, "alejandra": 1, "noem\u00e3\u00ad": 1, "reynoso": 1, "cotidiana": 1, "(soluci\u00e3\u00b3n": 1, "conflicto": 1, "familiares)": 1, "16;": 1, "17;": 1, "xxx": 6, "adecuarlas": 1, "familiar": 2, "adicionada": 1, "laura": 1, "ang\u00e3\u00a9lica": 1, "rojas": 1, "\u00e2\u0080\u009cdecreto": 2, "pol\u00e3\u00adtica-electoral\u00e2\u0080\u009d": 2, "2018-": 1, "madrid": 1, "dieciocho-": 1, "dr": 1, "prida-": 1, "extinci\u00e3\u00b3n": 5, "dominio": 5, "ordena": 1, "dictadas": 1, "ver\u00e3\u00a1n": 1, "2019-": 4, "mart\u00e3\u00ad": 1, "batres": 2, "guadarrama": 2, "antares": 2, "g": 2, "alatorre": 2, "lizeth": 1, "andr\u00e3\u00a9s": 2, "obrador-": 2, "secretaria": 2, "dra": 2, "olga": 2, "carmen": 2, "d\u00e3\u00a1vila-": 2, "guardia": 12, "10;": 1, "b);": 1, "35": 1, "xxiii;": 1, "21;": 1, "fuerza": 15, "detenciones": 2, "militar": 3, "naval": 3, "asumir\u00e3\u00a1": 1, "gradualidad": 1, "interinstitucional": 1, "formada": 1, "marina": 2, "armada": 4, "rango": 1, "prestaciones;": 1, "elemento": 1, "reasignado": 1, "contaba": 1, "asignado": 1, "elementos:": 2, "normativa": 1, "actuaci\u00e3\u00b3n": 4, "encargadas": 1, "doctrina": 1, "policial": 2, "municipios;": 1, "aportaciones": 1, "tareas": 4, "local;": 1, "relativo": 1, "jer\u00e3\u00a1rquica": 2, "reg\u00e3\u00admenes": 2, "ascensos": 2, "prestaciones": 2, "ingreso": 2, "profesionalizaci\u00e3\u00b3n": 2, "homologarse": 1, "permanente;": 1, "integrantes;": 2, "portaci\u00e3\u00b3n": 2, "armas": 6, "fuego": 3, "est\u00e3\u00a1ndares": 1, "internacionales;": 1, "delimitaci\u00e3\u00b3n": 1, "componentes": 1, "previsiones:": 2, "alcance": 1, "definici\u00e3\u00b3n": 1, "necesidad": 1, "racionalidad": 1, "oportunidad;": 1, "adiestramiento": 2, "m\u00e3\u00a9todos": 1, "t\u00e3\u00a1cticas": 1, "f\u00e3\u00adsico": 1, "empleo": 1, "incapacitantes": 2, "letales": 2, "letales;": 2, "distinci\u00e3\u00b3n": 1, "sanciones;": 1, "detenidas": 1, "custodia": 1, "manifestaciones": 1, "p\u00e3\u00bablicas;": 1, "sistematizaci\u00e3\u00b3n": 1, "archivo": 1, "b\u00e3\u00a1sicas": 1, "incorporar\u00e3\u00a1": 1, "rigen": 1, "conservaci\u00e3\u00b3n;": 1, "detenci\u00e3\u00b3n;": 1, "detenida": 1, "materia;": 1, "clasificar": 1, "reservada": 1, "confidencial;": 1, "autorizadas": 1, "acceso;": 1, "desempe\u00e3\u00b1en": 1, "desplegar": 1, "ocurrir": 1, "pongan": 1, "vulneren": 1, "desarrolla": 1, "regulada": 1, "fiscalizada": 1, "subordinada": 1, "complementaria": 1, "participar\u00e3\u00a1n": 1, "instrumentaci\u00e3\u00b3n": 1, "ejecutivos": 1, "presentar\u00e3\u00a1n": 1, "diagn\u00e3\u00b3stico": 1, "cuerpos": 1, "policiales": 1, "corresponsabilidad": 1, "haberse": 1, "emitido": 1, "enviar\u00e3\u00a1": 1, "avances": 1, "horizonte": 1, "marti": 1, "vazquez": 1}}